{
	"@main" : 	{
		"nodes" : {
			"%1" : {
				"type" : "ptr",
				"uses" : [2, 4, 5, 12, 15, 18],
				"uses deepness" : [0, 0, 0, 0, 0, 0]
			},
			"%2" : {
				"type" : "i32",
				"uses" : [3],
				"uses deepness" : [0]
			},
			"%3" : {
				"type" : "i32",
				"uses" : [4],
				"uses deepness" : [0]
			},
			"%4" : {
				"type" : "float*",
				"uses" : [5, 6],
				"uses deepness" : [0, 0]
			},
			"%5" : {
				"type" : "label",
				"uses" : [6, 7],
				"uses deepness" : [0, 0]
			},
			"%6" : {
				"type" : "label",
				"uses" : [7, 30],
				"uses deepness" : [0, 0]
			},
			"%21" : {
				"type" : "label",
				"uses" : [7, 30],
				"uses deepness" : [0, 0]
			},
			"%0" : {
				"type" : "label",
				"uses" : [9, 26],
				"uses deepness" : [0, 0]
			},
			"%7" : {
				"type" : "double",
				"uses" : [10, 11],
				"uses deepness" : [0, 0]
			},
			"%8" : {
				"type" : "double",
				"uses" : [11, 14],
				"uses deepness" : [0, 0]
			},
			"%9" : {
				"type" : "float*",
				"uses" : [12, 13],
				"uses deepness" : [0, 0]
			},
			"%10" : {
				"type" : "float",
				"uses" : [13, 14],
				"uses deepness" : [0, 0]
			},
			"%11" : {
				"type" : "double",
				"uses" : [14, 17],
				"uses deepness" : [0, 0]
			},
			"%12" : {
				"type" : "float*",
				"uses" : [15, 16],
				"uses deepness" : [0, 0]
			},
			"%13" : {
				"type" : "float",
				"uses" : [16, 17],
				"uses deepness" : [0, 0]
			},
			"%14" : {
				"type" : "double",
				"uses" : [17, 20],
				"uses deepness" : [0, 0]
			},
			"%15" : {
				"type" : "float*",
				"uses" : [18, 19],
				"uses deepness" : [0, 0]
			},
			"%16" : {
				"type" : "float",
				"uses" : [19, 20],
				"uses deepness" : [0, 0]
			},
			"%17" : {
				"type" : "double",
				"uses" : [20, 21],
				"uses deepness" : [0, 0]
			},
			"%18" : {
				"type" : "double",
				"uses" : [21, 22],
				"uses deepness" : [0, 0]
			},
			"%19" : {
				"type" : "float",
				"uses" : [22, 23],
				"uses deepness" : [0, 0]
			},
			"%20" : {
				"type" : "i32",
				"uses" : [23],
				"uses deepness" : [0]
			},
			"%23" : {
				"type" : "label",
				"uses" : [24, 28],
				"uses deepness" : [0, 0]
			},
			"%22" : {
				"type" : "i32",
				"uses" : [27],
				"uses deepness" : [0]
			}
		},
		"edges" : [
			{
				"node 1" : "%1",
				"node 2" : "%2"

			},
			{
				"node 1" : "%1",
				"node 2" : "%3"

			},
			{
				"node 1" : "%1",
				"node 2" : "%4"

			},
			{
				"node 1" : "%1",
				"node 2" : "%5"

			},
			{
				"node 1" : "%1",
				"node 2" : "%6"

			},
			{
				"node 1" : "%1",
				"node 2" : "%21"

			},
			{
				"node 1" : "%1",
				"node 2" : "%0"

			},
			{
				"node 1" : "%1",
				"node 2" : "%7"

			},
			{
				"node 1" : "%1",
				"node 2" : "%8"

			},
			{
				"node 1" : "%1",
				"node 2" : "%9"

			},
			{
				"node 1" : "%1",
				"node 2" : "%10"

			},
			{
				"node 1" : "%1",
				"node 2" : "%11"

			},
			{
				"node 1" : "%1",
				"node 2" : "%12"

			},
			{
				"node 1" : "%1",
				"node 2" : "%13"

			},
			{
				"node 1" : "%1",
				"node 2" : "%14"

			},
			{
				"node 1" : "%1",
				"node 2" : "%15"

			},
			{
				"node 1" : "%4",
				"node 2" : "%5"

			},
			{
				"node 1" : "%5",
				"node 2" : "%6"

			},
			{
				"node 1" : "%5",
				"node 2" : "%21"

			},
			{
				"node 1" : "%6",
				"node 2" : "%21"

			},
			{
				"node 1" : "%6",
				"node 2" : "%0"

			},
			{
				"node 1" : "%6",
				"node 2" : "%7"

			},
			{
				"node 1" : "%6",
				"node 2" : "%8"

			},
			{
				"node 1" : "%6",
				"node 2" : "%9"

			},
			{
				"node 1" : "%6",
				"node 2" : "%10"

			},
			{
				"node 1" : "%6",
				"node 2" : "%11"

			},
			{
				"node 1" : "%6",
				"node 2" : "%12"

			},
			{
				"node 1" : "%6",
				"node 2" : "%13"

			},
			{
				"node 1" : "%6",
				"node 2" : "%14"

			},
			{
				"node 1" : "%6",
				"node 2" : "%15"

			},
			{
				"node 1" : "%6",
				"node 2" : "%16"

			},
			{
				"node 1" : "%6",
				"node 2" : "%17"

			},
			{
				"node 1" : "%6",
				"node 2" : "%18"

			},
			{
				"node 1" : "%6",
				"node 2" : "%19"

			},
			{
				"node 1" : "%6",
				"node 2" : "%20"

			},
			{
				"node 1" : "%6",
				"node 2" : "%23"

			},
			{
				"node 1" : "%6",
				"node 2" : "%22"

			},
			{
				"node 1" : "%21",
				"node 2" : "%0"

			},
			{
				"node 1" : "%21",
				"node 2" : "%7"

			},
			{
				"node 1" : "%21",
				"node 2" : "%8"

			},
			{
				"node 1" : "%21",
				"node 2" : "%9"

			},
			{
				"node 1" : "%21",
				"node 2" : "%10"

			},
			{
				"node 1" : "%21",
				"node 2" : "%11"

			},
			{
				"node 1" : "%21",
				"node 2" : "%12"

			},
			{
				"node 1" : "%21",
				"node 2" : "%13"

			},
			{
				"node 1" : "%21",
				"node 2" : "%14"

			},
			{
				"node 1" : "%21",
				"node 2" : "%15"

			},
			{
				"node 1" : "%21",
				"node 2" : "%16"

			},
			{
				"node 1" : "%21",
				"node 2" : "%17"

			},
			{
				"node 1" : "%21",
				"node 2" : "%18"

			},
			{
				"node 1" : "%21",
				"node 2" : "%19"

			},
			{
				"node 1" : "%21",
				"node 2" : "%20"

			},
			{
				"node 1" : "%21",
				"node 2" : "%23"

			},
			{
				"node 1" : "%21",
				"node 2" : "%22"

			},
			{
				"node 1" : "%0",
				"node 2" : "%7"

			},
			{
				"node 1" : "%0",
				"node 2" : "%8"

			},
			{
				"node 1" : "%0",
				"node 2" : "%9"

			},
			{
				"node 1" : "%0",
				"node 2" : "%10"

			},
			{
				"node 1" : "%0",
				"node 2" : "%11"

			},
			{
				"node 1" : "%0",
				"node 2" : "%12"

			},
			{
				"node 1" : "%0",
				"node 2" : "%13"

			},
			{
				"node 1" : "%0",
				"node 2" : "%14"

			},
			{
				"node 1" : "%0",
				"node 2" : "%15"

			},
			{
				"node 1" : "%0",
				"node 2" : "%16"

			},
			{
				"node 1" : "%0",
				"node 2" : "%17"

			},
			{
				"node 1" : "%0",
				"node 2" : "%18"

			},
			{
				"node 1" : "%0",
				"node 2" : "%19"

			},
			{
				"node 1" : "%0",
				"node 2" : "%20"

			},
			{
				"node 1" : "%0",
				"node 2" : "%23"

			},
			{
				"node 1" : "%7",
				"node 2" : "%8"

			},
			{
				"node 1" : "%8",
				"node 2" : "%9"

			},
			{
				"node 1" : "%8",
				"node 2" : "%10"

			},
			{
				"node 1" : "%8",
				"node 2" : "%11"

			},
			{
				"node 1" : "%9",
				"node 2" : "%10"

			},
			{
				"node 1" : "%10",
				"node 2" : "%11"

			},
			{
				"node 1" : "%11",
				"node 2" : "%12"

			},
			{
				"node 1" : "%11",
				"node 2" : "%13"

			},
			{
				"node 1" : "%11",
				"node 2" : "%14"

			},
			{
				"node 1" : "%12",
				"node 2" : "%13"

			},
			{
				"node 1" : "%13",
				"node 2" : "%14"

			},
			{
				"node 1" : "%14",
				"node 2" : "%15"

			},
			{
				"node 1" : "%14",
				"node 2" : "%16"

			},
			{
				"node 1" : "%14",
				"node 2" : "%17"

			},
			{
				"node 1" : "%15",
				"node 2" : "%16"

			},
			{
				"node 1" : "%16",
				"node 2" : "%17"

			},
			{
				"node 1" : "%17",
				"node 2" : "%18"

			},
			{
				"node 1" : "%18",
				"node 2" : "%19"

			},
			{
				"node 1" : "%19",
				"node 2" : "%20"

			},
			{
				"node 1" : "%23",
				"node 2" : "%22"

			}
		]
	}
}