{
	"@main" : 	{
		"nodes" : {
			"%1" : {
				"type" : "ptr",
				"uses" : [2, 7, 20, 29, 52, 56, 93],
				"uses deepness" : [0, 0, 0, 0, 1, 1, 3]
			},
			"%2" : {
				"type" : "ptr",
				"uses" : [3, 88, 90],
				"uses deepness" : [0, 3, 3]
			},
			"%3" : {
				"type" : "label",
				"uses" : [4, 19, 24, 25, 100],
				"uses deepness" : [0, 0, 0, 0, 3]
			},
			"%57" : {
				"type" : "label",
				"uses" : [6, 68],
				"uses deepness" : [0, 3]
			},
			"%0" : {
				"type" : "label",
				"uses" : [6],
				"uses deepness" : [0]
			},
			"%4" : {
				"type" : "ptr",
				"uses" : [7, 8, 13],
				"uses deepness" : [0, 0, 0]
			},
			"%5" : {
				"type" : "",
				"uses" : [8, 9],
				"uses deepness" : [0, 0]
			},
			"%6" : {
				"type" : "",
				"uses" : [9, 10],
				"uses deepness" : [0, 0]
			},
			"%7" : {
				"type" : "ptr",
				"uses" : [10, 11],
				"uses deepness" : [0, 0]
			},
			"%8" : {
				"type" : "ptr",
				"uses" : [11, 12],
				"uses deepness" : [0, 0]
			},
			"%9" : {
				"type" : "ptr",
				"uses" : [12, 14],
				"uses deepness" : [0, 0]
			},
			"%10" : {
				"type" : "ptr",
				"uses" : [13, 14],
				"uses deepness" : [0, 0]
			},
			"%11" : {
				"type" : "ptr",
				"uses" : [14, 15],
				"uses deepness" : [0, 0]
			},
			"%12" : {
				"type" : "ptr",
				"uses" : [15, 16],
				"uses deepness" : [0, 0]
			},
			"%13" : {
				"type" : "label",
				"uses" : [16, 17],
				"uses deepness" : [0, 0]
			},
			"%14" : {
				"type" : "label",
				"uses" : [17, 24, 25],
				"uses deepness" : [0, 0, 0]
			},
			"%17" : {
				"type" : "label",
				"uses" : [17, 22, 28, 102],
				"uses deepness" : [0, 0, 0, 3]
			},
			"%15" : {
				"type" : "ptr",
				"uses" : [20, 21],
				"uses deepness" : [0, 0]
			},
			"%16" : {
				"type" : "i8",
				"uses" : [21, 25],
				"uses deepness" : [0, 0]
			},
			"%18" : {
				"type" : "label",
				"uses" : [25, 26],
				"uses deepness" : [0, 0]
			},
			"%19" : {
				"type" : "label",
				"uses" : [26, 38, 39],
				"uses deepness" : [0, 0, 1]
			},
			"%70" : {
				"type" : "label",
				"uses" : [26],
				"uses deepness" : [0]
			},
			"%20" : {
				"type" : "ptr",
				"uses" : [29, 30],
				"uses deepness" : [0, 0]
			},
			"%21" : {
				"type" : "i32",
				"uses" : [30, 32, 33, 59],
				"uses deepness" : [0, 0, 0, 1]
			},
			"%22" : {
				"type" : "ptr",
				"uses" : [31, 99],
				"uses deepness" : [0, 3]
			},
			"%23" : {
				"type" : "ptr",
				"uses" : [32, 35, 39, 54, 55, 61, 66],
				"uses deepness" : [0, 0, 1, 1, 1, 1, 3]
			},
			"%24" : {
				"type" : "i64",
				"uses" : [33, 34],
				"uses deepness" : [0, 0]
			},
			"%25" : {
				"type" : "i64",
				"uses" : [34, 35],
				"uses deepness" : [0, 0]
			},
			"%26" : {
				"type" : "ptr",
				"uses" : [35, 40],
				"uses deepness" : [0, 1]
			},
			"%27" : {
				"type" : "label",
				"uses" : [36, 43, 49, 51],
				"uses deepness" : [0, 1, 1, 1]
			},
			"%31" : {
				"type" : "label",
				"uses" : [38, 39, 45],
				"uses deepness" : [0, 1, 1]
			},
			"%.02" : {
				"type" : "ptr",
				"uses" : [39, 40, 44, 48],
				"uses deepness" : [1, 1, 1, 1]
			},
			"%32" : {
				"type" : "ptr",
				"uses" : [39, 48],
				"uses deepness" : [1, 1]
			},
			"%28" : {
				"type" : "label",
				"uses" : [40, 41],
				"uses deepness" : [1, 1]
			},
			"%29" : {
				"type" : "label",
				"uses" : [41, 47],
				"uses deepness" : [1, 1]
			},
			"%33" : {
				"type" : "label",
				"uses" : [41, 64, 65, 66],
				"uses deepness" : [1, 1, 2, 3]
			},
			"%30" : {
				"type" : "ptr",
				"uses" : [44],
				"uses deepness" : [1]
			},
			"%34" : {
				"type" : "ptr",
				"uses" : [52, 53],
				"uses deepness" : [1, 1]
			},
			"%35" : {
				"type" : "i32",
				"uses" : [53, 54],
				"uses deepness" : [1, 1]
			},
			"%36" : {
				"type" : "ptr",
				"uses" : [54, 55],
				"uses deepness" : [1, 1]
			},
			"%37" : {
				"type" : "double",
				"uses" : [55, 58],
				"uses deepness" : [1, 1]
			},
			"%38" : {
				"type" : "ptr",
				"uses" : [56, 57],
				"uses deepness" : [1, 1]
			},
			"%39" : {
				"type" : "i32",
				"uses" : [57, 58],
				"uses deepness" : [1, 1]
			},
			"%40" : {
				"type" : "double",
				"uses" : [58, 73, 76],
				"uses deepness" : [1, 3, 3]
			},
			"%41" : {
				"type" : "i64",
				"uses" : [59, 60],
				"uses deepness" : [1, 1]
			},
			"%42" : {
				"type" : "i64",
				"uses" : [60, 61],
				"uses deepness" : [1, 1]
			},
			"%43" : {
				"type" : "ptr",
				"uses" : [61, 67],
				"uses deepness" : [1, 3]
			},
			"%44" : {
				"type" : "label",
				"uses" : [62, 70, 83, 85],
				"uses deepness" : [1, 3, 3, 3]
			},
			"%55" : {
				"type" : "label",
				"uses" : [64, 65, 66, 79],
				"uses deepness" : [1, 2, 3, 3]
			},
			"%.01" : {
				"type" : "double",
				"uses" : [65, 78, 95],
				"uses deepness" : [2, 3, 3]
			},
			"%54" : {
				"type" : "double",
				"uses" : [65, 78],
				"uses deepness" : [2, 3]
			},
			"%.0" : {
				"type" : "ptr",
				"uses" : [66, 67, 71, 74, 82],
				"uses deepness" : [3, 3, 3, 3, 3]
			},
			"%56" : {
				"type" : "ptr",
				"uses" : [66, 82],
				"uses deepness" : [3, 3]
			},
			"%45" : {
				"type" : "label",
				"uses" : [67, 68],
				"uses deepness" : [3, 3]
			},
			"%46" : {
				"type" : "label",
				"uses" : [68, 81],
				"uses deepness" : [3, 3]
			},
			"%47" : {
				"type" : "ptr",
				"uses" : [71, 72],
				"uses deepness" : [3, 3]
			},
			"%48" : {
				"type" : "i32",
				"uses" : [72, 73],
				"uses deepness" : [3, 3]
			},
			"%49" : {
				"type" : "double",
				"uses" : [73, 77],
				"uses deepness" : [3, 3]
			},
			"%50" : {
				"type" : "ptr",
				"uses" : [74, 75],
				"uses deepness" : [3, 3]
			},
			"%51" : {
				"type" : "i32",
				"uses" : [75, 76],
				"uses deepness" : [3, 3]
			},
			"%52" : {
				"type" : "double",
				"uses" : [76, 77],
				"uses deepness" : [3, 3]
			},
			"%53" : {
				"type" : "double",
				"uses" : [77, 78],
				"uses deepness" : [3, 3]
			},
			"%58" : {
				"type" : "",
				"uses" : [86, 92],
				"uses deepness" : [3, 3]
			},
			"%59" : {
				"type" : "ptr",
				"uses" : [87, 89],
				"uses deepness" : [3, 3]
			},
			"%60" : {
				"type" : "ptr",
				"uses" : [88, 89],
				"uses deepness" : [3, 3]
			},
			"%61" : {
				"type" : "ptr",
				"uses" : [90, 91],
				"uses deepness" : [3, 3]
			},
			"%62" : {
				"type" : "ptr",
				"uses" : [91, 92],
				"uses deepness" : [3, 3]
			},
			"%63" : {
				"type" : "i32",
				"uses" : [92, 97],
				"uses deepness" : [3, 3]
			},
			"%64" : {
				"type" : "ptr",
				"uses" : [93, 94],
				"uses deepness" : [3, 3]
			},
			"%65" : {
				"type" : "i32",
				"uses" : [94, 95],
				"uses deepness" : [3, 3]
			},
			"%66" : {
				"type" : "double",
				"uses" : [95, 96],
				"uses deepness" : [3, 3]
			},
			"%67" : {
				"type" : "double",
				"uses" : [96, 97],
				"uses deepness" : [3, 3]
			},
			"%68" : {
				"type" : "double",
				"uses" : [97, 98],
				"uses deepness" : [3, 3]
			},
			"%69" : {
				"type" : "",
				"uses" : [98],
				"uses deepness" : [3]
			}
		},
		"edges" : [
			{
				"node 1" : "%1",
				"node 2" : "%2"

			},
			{
				"node 1" : "%1",
				"node 2" : "%3"

			},
			{
				"node 1" : "%1",
				"node 2" : "%57"

			},
			{
				"node 1" : "%1",
				"node 2" : "%0"

			},
			{
				"node 1" : "%1",
				"node 2" : "%4"

			},
			{
				"node 1" : "%1",
				"node 2" : "%5"

			},
			{
				"node 1" : "%1",
				"node 2" : "%6"

			},
			{
				"node 1" : "%1",
				"node 2" : "%7"

			},
			{
				"node 1" : "%1",
				"node 2" : "%8"

			},
			{
				"node 1" : "%1",
				"node 2" : "%9"

			},
			{
				"node 1" : "%1",
				"node 2" : "%10"

			},
			{
				"node 1" : "%1",
				"node 2" : "%11"

			},
			{
				"node 1" : "%1",
				"node 2" : "%12"

			},
			{
				"node 1" : "%1",
				"node 2" : "%13"

			},
			{
				"node 1" : "%1",
				"node 2" : "%14"

			},
			{
				"node 1" : "%1",
				"node 2" : "%17"

			},
			{
				"node 1" : "%1",
				"node 2" : "%15"

			},
			{
				"node 1" : "%1",
				"node 2" : "%16"

			},
			{
				"node 1" : "%1",
				"node 2" : "%18"

			},
			{
				"node 1" : "%1",
				"node 2" : "%19"

			},
			{
				"node 1" : "%1",
				"node 2" : "%70"

			},
			{
				"node 1" : "%1",
				"node 2" : "%20"

			},
			{
				"node 1" : "%1",
				"node 2" : "%21"

			},
			{
				"node 1" : "%1",
				"node 2" : "%22"

			},
			{
				"node 1" : "%1",
				"node 2" : "%23"

			},
			{
				"node 1" : "%1",
				"node 2" : "%24"

			},
			{
				"node 1" : "%1",
				"node 2" : "%25"

			},
			{
				"node 1" : "%1",
				"node 2" : "%26"

			},
			{
				"node 1" : "%1",
				"node 2" : "%27"

			},
			{
				"node 1" : "%1",
				"node 2" : "%31"

			},
			{
				"node 1" : "%1",
				"node 2" : "%.02"

			},
			{
				"node 1" : "%1",
				"node 2" : "%32"

			},
			{
				"node 1" : "%1",
				"node 2" : "%28"

			},
			{
				"node 1" : "%1",
				"node 2" : "%29"

			},
			{
				"node 1" : "%1",
				"node 2" : "%33"

			},
			{
				"node 1" : "%1",
				"node 2" : "%30"

			},
			{
				"node 1" : "%1",
				"node 2" : "%34"

			},
			{
				"node 1" : "%1",
				"node 2" : "%35"

			},
			{
				"node 1" : "%1",
				"node 2" : "%36"

			},
			{
				"node 1" : "%1",
				"node 2" : "%37"

			},
			{
				"node 1" : "%1",
				"node 2" : "%38"

			},
			{
				"node 1" : "%1",
				"node 2" : "%39"

			},
			{
				"node 1" : "%1",
				"node 2" : "%40"

			},
			{
				"node 1" : "%1",
				"node 2" : "%41"

			},
			{
				"node 1" : "%1",
				"node 2" : "%42"

			},
			{
				"node 1" : "%1",
				"node 2" : "%43"

			},
			{
				"node 1" : "%1",
				"node 2" : "%44"

			},
			{
				"node 1" : "%1",
				"node 2" : "%55"

			},
			{
				"node 1" : "%1",
				"node 2" : "%.01"

			},
			{
				"node 1" : "%1",
				"node 2" : "%54"

			},
			{
				"node 1" : "%1",
				"node 2" : "%.0"

			},
			{
				"node 1" : "%1",
				"node 2" : "%56"

			},
			{
				"node 1" : "%1",
				"node 2" : "%45"

			},
			{
				"node 1" : "%1",
				"node 2" : "%46"

			},
			{
				"node 1" : "%1",
				"node 2" : "%47"

			},
			{
				"node 1" : "%1",
				"node 2" : "%48"

			},
			{
				"node 1" : "%1",
				"node 2" : "%49"

			},
			{
				"node 1" : "%1",
				"node 2" : "%50"

			},
			{
				"node 1" : "%1",
				"node 2" : "%51"

			},
			{
				"node 1" : "%1",
				"node 2" : "%52"

			},
			{
				"node 1" : "%1",
				"node 2" : "%53"

			},
			{
				"node 1" : "%1",
				"node 2" : "%58"

			},
			{
				"node 1" : "%1",
				"node 2" : "%59"

			},
			{
				"node 1" : "%1",
				"node 2" : "%60"

			},
			{
				"node 1" : "%1",
				"node 2" : "%61"

			},
			{
				"node 1" : "%1",
				"node 2" : "%62"

			},
			{
				"node 1" : "%1",
				"node 2" : "%63"

			},
			{
				"node 1" : "%1",
				"node 2" : "%64"

			},
			{
				"node 1" : "%2",
				"node 2" : "%3"

			},
			{
				"node 1" : "%2",
				"node 2" : "%57"

			},
			{
				"node 1" : "%2",
				"node 2" : "%0"

			},
			{
				"node 1" : "%2",
				"node 2" : "%4"

			},
			{
				"node 1" : "%2",
				"node 2" : "%5"

			},
			{
				"node 1" : "%2",
				"node 2" : "%6"

			},
			{
				"node 1" : "%2",
				"node 2" : "%7"

			},
			{
				"node 1" : "%2",
				"node 2" : "%8"

			},
			{
				"node 1" : "%2",
				"node 2" : "%9"

			},
			{
				"node 1" : "%2",
				"node 2" : "%10"

			},
			{
				"node 1" : "%2",
				"node 2" : "%11"

			},
			{
				"node 1" : "%2",
				"node 2" : "%12"

			},
			{
				"node 1" : "%2",
				"node 2" : "%13"

			},
			{
				"node 1" : "%2",
				"node 2" : "%14"

			},
			{
				"node 1" : "%2",
				"node 2" : "%17"

			},
			{
				"node 1" : "%2",
				"node 2" : "%15"

			},
			{
				"node 1" : "%2",
				"node 2" : "%16"

			},
			{
				"node 1" : "%2",
				"node 2" : "%18"

			},
			{
				"node 1" : "%2",
				"node 2" : "%19"

			},
			{
				"node 1" : "%2",
				"node 2" : "%70"

			},
			{
				"node 1" : "%2",
				"node 2" : "%20"

			},
			{
				"node 1" : "%2",
				"node 2" : "%21"

			},
			{
				"node 1" : "%2",
				"node 2" : "%22"

			},
			{
				"node 1" : "%2",
				"node 2" : "%23"

			},
			{
				"node 1" : "%2",
				"node 2" : "%24"

			},
			{
				"node 1" : "%2",
				"node 2" : "%25"

			},
			{
				"node 1" : "%2",
				"node 2" : "%26"

			},
			{
				"node 1" : "%2",
				"node 2" : "%27"

			},
			{
				"node 1" : "%2",
				"node 2" : "%31"

			},
			{
				"node 1" : "%2",
				"node 2" : "%.02"

			},
			{
				"node 1" : "%2",
				"node 2" : "%32"

			},
			{
				"node 1" : "%2",
				"node 2" : "%28"

			},
			{
				"node 1" : "%2",
				"node 2" : "%29"

			},
			{
				"node 1" : "%2",
				"node 2" : "%33"

			},
			{
				"node 1" : "%2",
				"node 2" : "%30"

			},
			{
				"node 1" : "%2",
				"node 2" : "%34"

			},
			{
				"node 1" : "%2",
				"node 2" : "%35"

			},
			{
				"node 1" : "%2",
				"node 2" : "%36"

			},
			{
				"node 1" : "%2",
				"node 2" : "%37"

			},
			{
				"node 1" : "%2",
				"node 2" : "%38"

			},
			{
				"node 1" : "%2",
				"node 2" : "%39"

			},
			{
				"node 1" : "%2",
				"node 2" : "%40"

			},
			{
				"node 1" : "%2",
				"node 2" : "%41"

			},
			{
				"node 1" : "%2",
				"node 2" : "%42"

			},
			{
				"node 1" : "%2",
				"node 2" : "%43"

			},
			{
				"node 1" : "%2",
				"node 2" : "%44"

			},
			{
				"node 1" : "%2",
				"node 2" : "%55"

			},
			{
				"node 1" : "%2",
				"node 2" : "%.01"

			},
			{
				"node 1" : "%2",
				"node 2" : "%54"

			},
			{
				"node 1" : "%2",
				"node 2" : "%.0"

			},
			{
				"node 1" : "%2",
				"node 2" : "%56"

			},
			{
				"node 1" : "%2",
				"node 2" : "%45"

			},
			{
				"node 1" : "%2",
				"node 2" : "%46"

			},
			{
				"node 1" : "%2",
				"node 2" : "%47"

			},
			{
				"node 1" : "%2",
				"node 2" : "%48"

			},
			{
				"node 1" : "%2",
				"node 2" : "%49"

			},
			{
				"node 1" : "%2",
				"node 2" : "%50"

			},
			{
				"node 1" : "%2",
				"node 2" : "%51"

			},
			{
				"node 1" : "%2",
				"node 2" : "%52"

			},
			{
				"node 1" : "%2",
				"node 2" : "%53"

			},
			{
				"node 1" : "%2",
				"node 2" : "%58"

			},
			{
				"node 1" : "%2",
				"node 2" : "%59"

			},
			{
				"node 1" : "%2",
				"node 2" : "%60"

			},
			{
				"node 1" : "%2",
				"node 2" : "%61"

			},
			{
				"node 1" : "%3",
				"node 2" : "%57"

			},
			{
				"node 1" : "%3",
				"node 2" : "%0"

			},
			{
				"node 1" : "%3",
				"node 2" : "%4"

			},
			{
				"node 1" : "%3",
				"node 2" : "%5"

			},
			{
				"node 1" : "%3",
				"node 2" : "%6"

			},
			{
				"node 1" : "%3",
				"node 2" : "%7"

			},
			{
				"node 1" : "%3",
				"node 2" : "%8"

			},
			{
				"node 1" : "%3",
				"node 2" : "%9"

			},
			{
				"node 1" : "%3",
				"node 2" : "%10"

			},
			{
				"node 1" : "%3",
				"node 2" : "%11"

			},
			{
				"node 1" : "%3",
				"node 2" : "%12"

			},
			{
				"node 1" : "%3",
				"node 2" : "%13"

			},
			{
				"node 1" : "%3",
				"node 2" : "%14"

			},
			{
				"node 1" : "%3",
				"node 2" : "%17"

			},
			{
				"node 1" : "%3",
				"node 2" : "%15"

			},
			{
				"node 1" : "%3",
				"node 2" : "%16"

			},
			{
				"node 1" : "%3",
				"node 2" : "%18"

			},
			{
				"node 1" : "%3",
				"node 2" : "%19"

			},
			{
				"node 1" : "%3",
				"node 2" : "%70"

			},
			{
				"node 1" : "%3",
				"node 2" : "%20"

			},
			{
				"node 1" : "%3",
				"node 2" : "%21"

			},
			{
				"node 1" : "%3",
				"node 2" : "%22"

			},
			{
				"node 1" : "%3",
				"node 2" : "%23"

			},
			{
				"node 1" : "%3",
				"node 2" : "%24"

			},
			{
				"node 1" : "%3",
				"node 2" : "%25"

			},
			{
				"node 1" : "%3",
				"node 2" : "%26"

			},
			{
				"node 1" : "%3",
				"node 2" : "%27"

			},
			{
				"node 1" : "%3",
				"node 2" : "%31"

			},
			{
				"node 1" : "%3",
				"node 2" : "%.02"

			},
			{
				"node 1" : "%3",
				"node 2" : "%32"

			},
			{
				"node 1" : "%3",
				"node 2" : "%28"

			},
			{
				"node 1" : "%3",
				"node 2" : "%29"

			},
			{
				"node 1" : "%3",
				"node 2" : "%33"

			},
			{
				"node 1" : "%3",
				"node 2" : "%30"

			},
			{
				"node 1" : "%3",
				"node 2" : "%34"

			},
			{
				"node 1" : "%3",
				"node 2" : "%35"

			},
			{
				"node 1" : "%3",
				"node 2" : "%36"

			},
			{
				"node 1" : "%3",
				"node 2" : "%37"

			},
			{
				"node 1" : "%3",
				"node 2" : "%38"

			},
			{
				"node 1" : "%3",
				"node 2" : "%39"

			},
			{
				"node 1" : "%3",
				"node 2" : "%40"

			},
			{
				"node 1" : "%3",
				"node 2" : "%41"

			},
			{
				"node 1" : "%3",
				"node 2" : "%42"

			},
			{
				"node 1" : "%3",
				"node 2" : "%43"

			},
			{
				"node 1" : "%3",
				"node 2" : "%44"

			},
			{
				"node 1" : "%3",
				"node 2" : "%55"

			},
			{
				"node 1" : "%3",
				"node 2" : "%.01"

			},
			{
				"node 1" : "%3",
				"node 2" : "%54"

			},
			{
				"node 1" : "%3",
				"node 2" : "%.0"

			},
			{
				"node 1" : "%3",
				"node 2" : "%56"

			},
			{
				"node 1" : "%3",
				"node 2" : "%45"

			},
			{
				"node 1" : "%3",
				"node 2" : "%46"

			},
			{
				"node 1" : "%3",
				"node 2" : "%47"

			},
			{
				"node 1" : "%3",
				"node 2" : "%48"

			},
			{
				"node 1" : "%3",
				"node 2" : "%49"

			},
			{
				"node 1" : "%3",
				"node 2" : "%50"

			},
			{
				"node 1" : "%3",
				"node 2" : "%51"

			},
			{
				"node 1" : "%3",
				"node 2" : "%52"

			},
			{
				"node 1" : "%3",
				"node 2" : "%53"

			},
			{
				"node 1" : "%3",
				"node 2" : "%58"

			},
			{
				"node 1" : "%3",
				"node 2" : "%59"

			},
			{
				"node 1" : "%3",
				"node 2" : "%60"

			},
			{
				"node 1" : "%3",
				"node 2" : "%61"

			},
			{
				"node 1" : "%3",
				"node 2" : "%62"

			},
			{
				"node 1" : "%3",
				"node 2" : "%63"

			},
			{
				"node 1" : "%3",
				"node 2" : "%64"

			},
			{
				"node 1" : "%3",
				"node 2" : "%65"

			},
			{
				"node 1" : "%3",
				"node 2" : "%66"

			},
			{
				"node 1" : "%3",
				"node 2" : "%67"

			},
			{
				"node 1" : "%3",
				"node 2" : "%68"

			},
			{
				"node 1" : "%3",
				"node 2" : "%69"

			},
			{
				"node 1" : "%57",
				"node 2" : "%0"

			},
			{
				"node 1" : "%57",
				"node 2" : "%4"

			},
			{
				"node 1" : "%57",
				"node 2" : "%5"

			},
			{
				"node 1" : "%57",
				"node 2" : "%6"

			},
			{
				"node 1" : "%57",
				"node 2" : "%7"

			},
			{
				"node 1" : "%57",
				"node 2" : "%8"

			},
			{
				"node 1" : "%57",
				"node 2" : "%9"

			},
			{
				"node 1" : "%57",
				"node 2" : "%10"

			},
			{
				"node 1" : "%57",
				"node 2" : "%11"

			},
			{
				"node 1" : "%57",
				"node 2" : "%12"

			},
			{
				"node 1" : "%57",
				"node 2" : "%13"

			},
			{
				"node 1" : "%57",
				"node 2" : "%14"

			},
			{
				"node 1" : "%57",
				"node 2" : "%17"

			},
			{
				"node 1" : "%57",
				"node 2" : "%15"

			},
			{
				"node 1" : "%57",
				"node 2" : "%16"

			},
			{
				"node 1" : "%57",
				"node 2" : "%18"

			},
			{
				"node 1" : "%57",
				"node 2" : "%19"

			},
			{
				"node 1" : "%57",
				"node 2" : "%70"

			},
			{
				"node 1" : "%57",
				"node 2" : "%20"

			},
			{
				"node 1" : "%57",
				"node 2" : "%21"

			},
			{
				"node 1" : "%57",
				"node 2" : "%22"

			},
			{
				"node 1" : "%57",
				"node 2" : "%23"

			},
			{
				"node 1" : "%57",
				"node 2" : "%24"

			},
			{
				"node 1" : "%57",
				"node 2" : "%25"

			},
			{
				"node 1" : "%57",
				"node 2" : "%26"

			},
			{
				"node 1" : "%57",
				"node 2" : "%27"

			},
			{
				"node 1" : "%57",
				"node 2" : "%31"

			},
			{
				"node 1" : "%57",
				"node 2" : "%.02"

			},
			{
				"node 1" : "%57",
				"node 2" : "%32"

			},
			{
				"node 1" : "%57",
				"node 2" : "%28"

			},
			{
				"node 1" : "%57",
				"node 2" : "%29"

			},
			{
				"node 1" : "%57",
				"node 2" : "%33"

			},
			{
				"node 1" : "%57",
				"node 2" : "%30"

			},
			{
				"node 1" : "%57",
				"node 2" : "%34"

			},
			{
				"node 1" : "%57",
				"node 2" : "%35"

			},
			{
				"node 1" : "%57",
				"node 2" : "%36"

			},
			{
				"node 1" : "%57",
				"node 2" : "%37"

			},
			{
				"node 1" : "%57",
				"node 2" : "%38"

			},
			{
				"node 1" : "%57",
				"node 2" : "%39"

			},
			{
				"node 1" : "%57",
				"node 2" : "%40"

			},
			{
				"node 1" : "%57",
				"node 2" : "%41"

			},
			{
				"node 1" : "%57",
				"node 2" : "%42"

			},
			{
				"node 1" : "%57",
				"node 2" : "%43"

			},
			{
				"node 1" : "%57",
				"node 2" : "%44"

			},
			{
				"node 1" : "%57",
				"node 2" : "%55"

			},
			{
				"node 1" : "%57",
				"node 2" : "%.01"

			},
			{
				"node 1" : "%57",
				"node 2" : "%54"

			},
			{
				"node 1" : "%57",
				"node 2" : "%.0"

			},
			{
				"node 1" : "%57",
				"node 2" : "%56"

			},
			{
				"node 1" : "%57",
				"node 2" : "%45"

			},
			{
				"node 1" : "%57",
				"node 2" : "%46"

			},
			{
				"node 1" : "%4",
				"node 2" : "%5"

			},
			{
				"node 1" : "%4",
				"node 2" : "%6"

			},
			{
				"node 1" : "%4",
				"node 2" : "%7"

			},
			{
				"node 1" : "%4",
				"node 2" : "%8"

			},
			{
				"node 1" : "%4",
				"node 2" : "%9"

			},
			{
				"node 1" : "%4",
				"node 2" : "%10"

			},
			{
				"node 1" : "%5",
				"node 2" : "%6"

			},
			{
				"node 1" : "%6",
				"node 2" : "%7"

			},
			{
				"node 1" : "%7",
				"node 2" : "%8"

			},
			{
				"node 1" : "%8",
				"node 2" : "%9"

			},
			{
				"node 1" : "%9",
				"node 2" : "%10"

			},
			{
				"node 1" : "%9",
				"node 2" : "%11"

			},
			{
				"node 1" : "%10",
				"node 2" : "%11"

			},
			{
				"node 1" : "%11",
				"node 2" : "%12"

			},
			{
				"node 1" : "%12",
				"node 2" : "%13"

			},
			{
				"node 1" : "%13",
				"node 2" : "%14"

			},
			{
				"node 1" : "%13",
				"node 2" : "%17"

			},
			{
				"node 1" : "%14",
				"node 2" : "%17"

			},
			{
				"node 1" : "%14",
				"node 2" : "%15"

			},
			{
				"node 1" : "%14",
				"node 2" : "%16"

			},
			{
				"node 1" : "%14",
				"node 2" : "%18"

			},
			{
				"node 1" : "%17",
				"node 2" : "%15"

			},
			{
				"node 1" : "%17",
				"node 2" : "%16"

			},
			{
				"node 1" : "%17",
				"node 2" : "%18"

			},
			{
				"node 1" : "%17",
				"node 2" : "%19"

			},
			{
				"node 1" : "%17",
				"node 2" : "%70"

			},
			{
				"node 1" : "%17",
				"node 2" : "%20"

			},
			{
				"node 1" : "%17",
				"node 2" : "%21"

			},
			{
				"node 1" : "%17",
				"node 2" : "%22"

			},
			{
				"node 1" : "%17",
				"node 2" : "%23"

			},
			{
				"node 1" : "%17",
				"node 2" : "%24"

			},
			{
				"node 1" : "%17",
				"node 2" : "%25"

			},
			{
				"node 1" : "%17",
				"node 2" : "%26"

			},
			{
				"node 1" : "%17",
				"node 2" : "%27"

			},
			{
				"node 1" : "%17",
				"node 2" : "%31"

			},
			{
				"node 1" : "%17",
				"node 2" : "%.02"

			},
			{
				"node 1" : "%17",
				"node 2" : "%32"

			},
			{
				"node 1" : "%17",
				"node 2" : "%28"

			},
			{
				"node 1" : "%17",
				"node 2" : "%29"

			},
			{
				"node 1" : "%17",
				"node 2" : "%33"

			},
			{
				"node 1" : "%17",
				"node 2" : "%30"

			},
			{
				"node 1" : "%17",
				"node 2" : "%34"

			},
			{
				"node 1" : "%17",
				"node 2" : "%35"

			},
			{
				"node 1" : "%17",
				"node 2" : "%36"

			},
			{
				"node 1" : "%17",
				"node 2" : "%37"

			},
			{
				"node 1" : "%17",
				"node 2" : "%38"

			},
			{
				"node 1" : "%17",
				"node 2" : "%39"

			},
			{
				"node 1" : "%17",
				"node 2" : "%40"

			},
			{
				"node 1" : "%17",
				"node 2" : "%41"

			},
			{
				"node 1" : "%17",
				"node 2" : "%42"

			},
			{
				"node 1" : "%17",
				"node 2" : "%43"

			},
			{
				"node 1" : "%17",
				"node 2" : "%44"

			},
			{
				"node 1" : "%17",
				"node 2" : "%55"

			},
			{
				"node 1" : "%17",
				"node 2" : "%.01"

			},
			{
				"node 1" : "%17",
				"node 2" : "%54"

			},
			{
				"node 1" : "%17",
				"node 2" : "%.0"

			},
			{
				"node 1" : "%17",
				"node 2" : "%56"

			},
			{
				"node 1" : "%17",
				"node 2" : "%45"

			},
			{
				"node 1" : "%17",
				"node 2" : "%46"

			},
			{
				"node 1" : "%17",
				"node 2" : "%47"

			},
			{
				"node 1" : "%17",
				"node 2" : "%48"

			},
			{
				"node 1" : "%17",
				"node 2" : "%49"

			},
			{
				"node 1" : "%17",
				"node 2" : "%50"

			},
			{
				"node 1" : "%17",
				"node 2" : "%51"

			},
			{
				"node 1" : "%17",
				"node 2" : "%52"

			},
			{
				"node 1" : "%17",
				"node 2" : "%53"

			},
			{
				"node 1" : "%17",
				"node 2" : "%58"

			},
			{
				"node 1" : "%17",
				"node 2" : "%59"

			},
			{
				"node 1" : "%17",
				"node 2" : "%60"

			},
			{
				"node 1" : "%17",
				"node 2" : "%61"

			},
			{
				"node 1" : "%17",
				"node 2" : "%62"

			},
			{
				"node 1" : "%17",
				"node 2" : "%63"

			},
			{
				"node 1" : "%17",
				"node 2" : "%64"

			},
			{
				"node 1" : "%17",
				"node 2" : "%65"

			},
			{
				"node 1" : "%17",
				"node 2" : "%66"

			},
			{
				"node 1" : "%17",
				"node 2" : "%67"

			},
			{
				"node 1" : "%17",
				"node 2" : "%68"

			},
			{
				"node 1" : "%17",
				"node 2" : "%69"

			},
			{
				"node 1" : "%15",
				"node 2" : "%16"

			},
			{
				"node 1" : "%16",
				"node 2" : "%18"

			},
			{
				"node 1" : "%18",
				"node 2" : "%19"

			},
			{
				"node 1" : "%18",
				"node 2" : "%70"

			},
			{
				"node 1" : "%19",
				"node 2" : "%70"

			},
			{
				"node 1" : "%19",
				"node 2" : "%20"

			},
			{
				"node 1" : "%19",
				"node 2" : "%21"

			},
			{
				"node 1" : "%19",
				"node 2" : "%22"

			},
			{
				"node 1" : "%19",
				"node 2" : "%23"

			},
			{
				"node 1" : "%19",
				"node 2" : "%24"

			},
			{
				"node 1" : "%19",
				"node 2" : "%25"

			},
			{
				"node 1" : "%19",
				"node 2" : "%26"

			},
			{
				"node 1" : "%19",
				"node 2" : "%27"

			},
			{
				"node 1" : "%19",
				"node 2" : "%31"

			},
			{
				"node 1" : "%19",
				"node 2" : "%.02"

			},
			{
				"node 1" : "%19",
				"node 2" : "%32"

			},
			{
				"node 1" : "%20",
				"node 2" : "%21"

			},
			{
				"node 1" : "%21",
				"node 2" : "%22"

			},
			{
				"node 1" : "%21",
				"node 2" : "%23"

			},
			{
				"node 1" : "%21",
				"node 2" : "%24"

			},
			{
				"node 1" : "%21",
				"node 2" : "%25"

			},
			{
				"node 1" : "%21",
				"node 2" : "%26"

			},
			{
				"node 1" : "%21",
				"node 2" : "%27"

			},
			{
				"node 1" : "%21",
				"node 2" : "%31"

			},
			{
				"node 1" : "%21",
				"node 2" : "%.02"

			},
			{
				"node 1" : "%21",
				"node 2" : "%32"

			},
			{
				"node 1" : "%21",
				"node 2" : "%28"

			},
			{
				"node 1" : "%21",
				"node 2" : "%29"

			},
			{
				"node 1" : "%21",
				"node 2" : "%33"

			},
			{
				"node 1" : "%21",
				"node 2" : "%30"

			},
			{
				"node 1" : "%21",
				"node 2" : "%34"

			},
			{
				"node 1" : "%21",
				"node 2" : "%35"

			},
			{
				"node 1" : "%21",
				"node 2" : "%36"

			},
			{
				"node 1" : "%21",
				"node 2" : "%37"

			},
			{
				"node 1" : "%21",
				"node 2" : "%38"

			},
			{
				"node 1" : "%21",
				"node 2" : "%39"

			},
			{
				"node 1" : "%21",
				"node 2" : "%40"

			},
			{
				"node 1" : "%21",
				"node 2" : "%41"

			},
			{
				"node 1" : "%22",
				"node 2" : "%23"

			},
			{
				"node 1" : "%22",
				"node 2" : "%24"

			},
			{
				"node 1" : "%22",
				"node 2" : "%25"

			},
			{
				"node 1" : "%22",
				"node 2" : "%26"

			},
			{
				"node 1" : "%22",
				"node 2" : "%27"

			},
			{
				"node 1" : "%22",
				"node 2" : "%31"

			},
			{
				"node 1" : "%22",
				"node 2" : "%.02"

			},
			{
				"node 1" : "%22",
				"node 2" : "%32"

			},
			{
				"node 1" : "%22",
				"node 2" : "%28"

			},
			{
				"node 1" : "%22",
				"node 2" : "%29"

			},
			{
				"node 1" : "%22",
				"node 2" : "%33"

			},
			{
				"node 1" : "%22",
				"node 2" : "%30"

			},
			{
				"node 1" : "%22",
				"node 2" : "%34"

			},
			{
				"node 1" : "%22",
				"node 2" : "%35"

			},
			{
				"node 1" : "%22",
				"node 2" : "%36"

			},
			{
				"node 1" : "%22",
				"node 2" : "%37"

			},
			{
				"node 1" : "%22",
				"node 2" : "%38"

			},
			{
				"node 1" : "%22",
				"node 2" : "%39"

			},
			{
				"node 1" : "%22",
				"node 2" : "%40"

			},
			{
				"node 1" : "%22",
				"node 2" : "%41"

			},
			{
				"node 1" : "%22",
				"node 2" : "%42"

			},
			{
				"node 1" : "%22",
				"node 2" : "%43"

			},
			{
				"node 1" : "%22",
				"node 2" : "%44"

			},
			{
				"node 1" : "%22",
				"node 2" : "%55"

			},
			{
				"node 1" : "%22",
				"node 2" : "%.01"

			},
			{
				"node 1" : "%22",
				"node 2" : "%54"

			},
			{
				"node 1" : "%22",
				"node 2" : "%.0"

			},
			{
				"node 1" : "%22",
				"node 2" : "%56"

			},
			{
				"node 1" : "%22",
				"node 2" : "%45"

			},
			{
				"node 1" : "%22",
				"node 2" : "%46"

			},
			{
				"node 1" : "%22",
				"node 2" : "%47"

			},
			{
				"node 1" : "%22",
				"node 2" : "%48"

			},
			{
				"node 1" : "%22",
				"node 2" : "%49"

			},
			{
				"node 1" : "%22",
				"node 2" : "%50"

			},
			{
				"node 1" : "%22",
				"node 2" : "%51"

			},
			{
				"node 1" : "%22",
				"node 2" : "%52"

			},
			{
				"node 1" : "%22",
				"node 2" : "%53"

			},
			{
				"node 1" : "%22",
				"node 2" : "%58"

			},
			{
				"node 1" : "%22",
				"node 2" : "%59"

			},
			{
				"node 1" : "%22",
				"node 2" : "%60"

			},
			{
				"node 1" : "%22",
				"node 2" : "%61"

			},
			{
				"node 1" : "%22",
				"node 2" : "%62"

			},
			{
				"node 1" : "%22",
				"node 2" : "%63"

			},
			{
				"node 1" : "%22",
				"node 2" : "%64"

			},
			{
				"node 1" : "%22",
				"node 2" : "%65"

			},
			{
				"node 1" : "%22",
				"node 2" : "%66"

			},
			{
				"node 1" : "%22",
				"node 2" : "%67"

			},
			{
				"node 1" : "%22",
				"node 2" : "%68"

			},
			{
				"node 1" : "%22",
				"node 2" : "%69"

			},
			{
				"node 1" : "%23",
				"node 2" : "%24"

			},
			{
				"node 1" : "%23",
				"node 2" : "%25"

			},
			{
				"node 1" : "%23",
				"node 2" : "%26"

			},
			{
				"node 1" : "%23",
				"node 2" : "%27"

			},
			{
				"node 1" : "%23",
				"node 2" : "%31"

			},
			{
				"node 1" : "%23",
				"node 2" : "%.02"

			},
			{
				"node 1" : "%23",
				"node 2" : "%32"

			},
			{
				"node 1" : "%23",
				"node 2" : "%28"

			},
			{
				"node 1" : "%23",
				"node 2" : "%29"

			},
			{
				"node 1" : "%23",
				"node 2" : "%33"

			},
			{
				"node 1" : "%23",
				"node 2" : "%30"

			},
			{
				"node 1" : "%23",
				"node 2" : "%34"

			},
			{
				"node 1" : "%23",
				"node 2" : "%35"

			},
			{
				"node 1" : "%23",
				"node 2" : "%36"

			},
			{
				"node 1" : "%23",
				"node 2" : "%37"

			},
			{
				"node 1" : "%23",
				"node 2" : "%38"

			},
			{
				"node 1" : "%23",
				"node 2" : "%39"

			},
			{
				"node 1" : "%23",
				"node 2" : "%40"

			},
			{
				"node 1" : "%23",
				"node 2" : "%41"

			},
			{
				"node 1" : "%23",
				"node 2" : "%42"

			},
			{
				"node 1" : "%23",
				"node 2" : "%43"

			},
			{
				"node 1" : "%23",
				"node 2" : "%44"

			},
			{
				"node 1" : "%23",
				"node 2" : "%55"

			},
			{
				"node 1" : "%23",
				"node 2" : "%.01"

			},
			{
				"node 1" : "%23",
				"node 2" : "%54"

			},
			{
				"node 1" : "%23",
				"node 2" : "%.0"

			},
			{
				"node 1" : "%23",
				"node 2" : "%56"

			},
			{
				"node 1" : "%24",
				"node 2" : "%25"

			},
			{
				"node 1" : "%25",
				"node 2" : "%26"

			},
			{
				"node 1" : "%26",
				"node 2" : "%27"

			},
			{
				"node 1" : "%26",
				"node 2" : "%31"

			},
			{
				"node 1" : "%26",
				"node 2" : "%.02"

			},
			{
				"node 1" : "%26",
				"node 2" : "%32"

			},
			{
				"node 1" : "%26",
				"node 2" : "%28"

			},
			{
				"node 1" : "%27",
				"node 2" : "%31"

			},
			{
				"node 1" : "%27",
				"node 2" : "%.02"

			},
			{
				"node 1" : "%27",
				"node 2" : "%32"

			},
			{
				"node 1" : "%27",
				"node 2" : "%28"

			},
			{
				"node 1" : "%27",
				"node 2" : "%29"

			},
			{
				"node 1" : "%27",
				"node 2" : "%33"

			},
			{
				"node 1" : "%27",
				"node 2" : "%30"

			},
			{
				"node 1" : "%31",
				"node 2" : "%.02"

			},
			{
				"node 1" : "%31",
				"node 2" : "%32"

			},
			{
				"node 1" : "%31",
				"node 2" : "%28"

			},
			{
				"node 1" : "%31",
				"node 2" : "%29"

			},
			{
				"node 1" : "%31",
				"node 2" : "%33"

			},
			{
				"node 1" : "%31",
				"node 2" : "%30"

			},
			{
				"node 1" : "%.02",
				"node 2" : "%32"

			},
			{
				"node 1" : "%.02",
				"node 2" : "%28"

			},
			{
				"node 1" : "%.02",
				"node 2" : "%29"

			},
			{
				"node 1" : "%.02",
				"node 2" : "%33"

			},
			{
				"node 1" : "%.02",
				"node 2" : "%30"

			},
			{
				"node 1" : "%32",
				"node 2" : "%28"

			},
			{
				"node 1" : "%32",
				"node 2" : "%29"

			},
			{
				"node 1" : "%32",
				"node 2" : "%33"

			},
			{
				"node 1" : "%32",
				"node 2" : "%30"

			},
			{
				"node 1" : "%28",
				"node 2" : "%29"

			},
			{
				"node 1" : "%28",
				"node 2" : "%33"

			},
			{
				"node 1" : "%29",
				"node 2" : "%33"

			},
			{
				"node 1" : "%29",
				"node 2" : "%30"

			},
			{
				"node 1" : "%33",
				"node 2" : "%30"

			},
			{
				"node 1" : "%33",
				"node 2" : "%34"

			},
			{
				"node 1" : "%33",
				"node 2" : "%35"

			},
			{
				"node 1" : "%33",
				"node 2" : "%36"

			},
			{
				"node 1" : "%33",
				"node 2" : "%37"

			},
			{
				"node 1" : "%33",
				"node 2" : "%38"

			},
			{
				"node 1" : "%33",
				"node 2" : "%39"

			},
			{
				"node 1" : "%33",
				"node 2" : "%40"

			},
			{
				"node 1" : "%33",
				"node 2" : "%41"

			},
			{
				"node 1" : "%33",
				"node 2" : "%42"

			},
			{
				"node 1" : "%33",
				"node 2" : "%43"

			},
			{
				"node 1" : "%33",
				"node 2" : "%44"

			},
			{
				"node 1" : "%33",
				"node 2" : "%55"

			},
			{
				"node 1" : "%33",
				"node 2" : "%.01"

			},
			{
				"node 1" : "%33",
				"node 2" : "%54"

			},
			{
				"node 1" : "%33",
				"node 2" : "%.0"

			},
			{
				"node 1" : "%33",
				"node 2" : "%56"

			},
			{
				"node 1" : "%34",
				"node 2" : "%35"

			},
			{
				"node 1" : "%35",
				"node 2" : "%36"

			},
			{
				"node 1" : "%36",
				"node 2" : "%37"

			},
			{
				"node 1" : "%37",
				"node 2" : "%38"

			},
			{
				"node 1" : "%37",
				"node 2" : "%39"

			},
			{
				"node 1" : "%37",
				"node 2" : "%40"

			},
			{
				"node 1" : "%38",
				"node 2" : "%39"

			},
			{
				"node 1" : "%39",
				"node 2" : "%40"

			},
			{
				"node 1" : "%40",
				"node 2" : "%41"

			},
			{
				"node 1" : "%40",
				"node 2" : "%42"

			},
			{
				"node 1" : "%40",
				"node 2" : "%43"

			},
			{
				"node 1" : "%40",
				"node 2" : "%44"

			},
			{
				"node 1" : "%40",
				"node 2" : "%55"

			},
			{
				"node 1" : "%40",
				"node 2" : "%.01"

			},
			{
				"node 1" : "%40",
				"node 2" : "%54"

			},
			{
				"node 1" : "%40",
				"node 2" : "%.0"

			},
			{
				"node 1" : "%40",
				"node 2" : "%56"

			},
			{
				"node 1" : "%40",
				"node 2" : "%45"

			},
			{
				"node 1" : "%40",
				"node 2" : "%46"

			},
			{
				"node 1" : "%40",
				"node 2" : "%47"

			},
			{
				"node 1" : "%40",
				"node 2" : "%48"

			},
			{
				"node 1" : "%40",
				"node 2" : "%49"

			},
			{
				"node 1" : "%40",
				"node 2" : "%50"

			},
			{
				"node 1" : "%40",
				"node 2" : "%51"

			},
			{
				"node 1" : "%40",
				"node 2" : "%52"

			},
			{
				"node 1" : "%41",
				"node 2" : "%42"

			},
			{
				"node 1" : "%42",
				"node 2" : "%43"

			},
			{
				"node 1" : "%43",
				"node 2" : "%44"

			},
			{
				"node 1" : "%43",
				"node 2" : "%55"

			},
			{
				"node 1" : "%43",
				"node 2" : "%.01"

			},
			{
				"node 1" : "%43",
				"node 2" : "%54"

			},
			{
				"node 1" : "%43",
				"node 2" : "%.0"

			},
			{
				"node 1" : "%43",
				"node 2" : "%56"

			},
			{
				"node 1" : "%43",
				"node 2" : "%45"

			},
			{
				"node 1" : "%44",
				"node 2" : "%55"

			},
			{
				"node 1" : "%44",
				"node 2" : "%.01"

			},
			{
				"node 1" : "%44",
				"node 2" : "%54"

			},
			{
				"node 1" : "%44",
				"node 2" : "%.0"

			},
			{
				"node 1" : "%44",
				"node 2" : "%56"

			},
			{
				"node 1" : "%44",
				"node 2" : "%45"

			},
			{
				"node 1" : "%44",
				"node 2" : "%46"

			},
			{
				"node 1" : "%44",
				"node 2" : "%47"

			},
			{
				"node 1" : "%44",
				"node 2" : "%48"

			},
			{
				"node 1" : "%44",
				"node 2" : "%49"

			},
			{
				"node 1" : "%44",
				"node 2" : "%50"

			},
			{
				"node 1" : "%44",
				"node 2" : "%51"

			},
			{
				"node 1" : "%44",
				"node 2" : "%52"

			},
			{
				"node 1" : "%44",
				"node 2" : "%53"

			},
			{
				"node 1" : "%55",
				"node 2" : "%.01"

			},
			{
				"node 1" : "%55",
				"node 2" : "%54"

			},
			{
				"node 1" : "%55",
				"node 2" : "%.0"

			},
			{
				"node 1" : "%55",
				"node 2" : "%56"

			},
			{
				"node 1" : "%55",
				"node 2" : "%45"

			},
			{
				"node 1" : "%55",
				"node 2" : "%46"

			},
			{
				"node 1" : "%55",
				"node 2" : "%47"

			},
			{
				"node 1" : "%55",
				"node 2" : "%48"

			},
			{
				"node 1" : "%55",
				"node 2" : "%49"

			},
			{
				"node 1" : "%55",
				"node 2" : "%50"

			},
			{
				"node 1" : "%55",
				"node 2" : "%51"

			},
			{
				"node 1" : "%55",
				"node 2" : "%52"

			},
			{
				"node 1" : "%55",
				"node 2" : "%53"

			},
			{
				"node 1" : "%.01",
				"node 2" : "%54"

			},
			{
				"node 1" : "%.01",
				"node 2" : "%.0"

			},
			{
				"node 1" : "%.01",
				"node 2" : "%56"

			},
			{
				"node 1" : "%.01",
				"node 2" : "%45"

			},
			{
				"node 1" : "%.01",
				"node 2" : "%46"

			},
			{
				"node 1" : "%.01",
				"node 2" : "%47"

			},
			{
				"node 1" : "%.01",
				"node 2" : "%48"

			},
			{
				"node 1" : "%.01",
				"node 2" : "%49"

			},
			{
				"node 1" : "%.01",
				"node 2" : "%50"

			},
			{
				"node 1" : "%.01",
				"node 2" : "%51"

			},
			{
				"node 1" : "%.01",
				"node 2" : "%52"

			},
			{
				"node 1" : "%.01",
				"node 2" : "%53"

			},
			{
				"node 1" : "%.01",
				"node 2" : "%58"

			},
			{
				"node 1" : "%.01",
				"node 2" : "%59"

			},
			{
				"node 1" : "%.01",
				"node 2" : "%60"

			},
			{
				"node 1" : "%.01",
				"node 2" : "%61"

			},
			{
				"node 1" : "%.01",
				"node 2" : "%62"

			},
			{
				"node 1" : "%.01",
				"node 2" : "%63"

			},
			{
				"node 1" : "%.01",
				"node 2" : "%64"

			},
			{
				"node 1" : "%.01",
				"node 2" : "%65"

			},
			{
				"node 1" : "%.01",
				"node 2" : "%66"

			},
			{
				"node 1" : "%54",
				"node 2" : "%.0"

			},
			{
				"node 1" : "%54",
				"node 2" : "%56"

			},
			{
				"node 1" : "%54",
				"node 2" : "%45"

			},
			{
				"node 1" : "%54",
				"node 2" : "%46"

			},
			{
				"node 1" : "%54",
				"node 2" : "%47"

			},
			{
				"node 1" : "%54",
				"node 2" : "%48"

			},
			{
				"node 1" : "%54",
				"node 2" : "%49"

			},
			{
				"node 1" : "%54",
				"node 2" : "%50"

			},
			{
				"node 1" : "%54",
				"node 2" : "%51"

			},
			{
				"node 1" : "%54",
				"node 2" : "%52"

			},
			{
				"node 1" : "%54",
				"node 2" : "%53"

			},
			{
				"node 1" : "%.0",
				"node 2" : "%56"

			},
			{
				"node 1" : "%.0",
				"node 2" : "%45"

			},
			{
				"node 1" : "%.0",
				"node 2" : "%46"

			},
			{
				"node 1" : "%.0",
				"node 2" : "%47"

			},
			{
				"node 1" : "%.0",
				"node 2" : "%48"

			},
			{
				"node 1" : "%.0",
				"node 2" : "%49"

			},
			{
				"node 1" : "%.0",
				"node 2" : "%50"

			},
			{
				"node 1" : "%.0",
				"node 2" : "%51"

			},
			{
				"node 1" : "%.0",
				"node 2" : "%52"

			},
			{
				"node 1" : "%.0",
				"node 2" : "%53"

			},
			{
				"node 1" : "%56",
				"node 2" : "%45"

			},
			{
				"node 1" : "%56",
				"node 2" : "%46"

			},
			{
				"node 1" : "%56",
				"node 2" : "%47"

			},
			{
				"node 1" : "%56",
				"node 2" : "%48"

			},
			{
				"node 1" : "%56",
				"node 2" : "%49"

			},
			{
				"node 1" : "%56",
				"node 2" : "%50"

			},
			{
				"node 1" : "%56",
				"node 2" : "%51"

			},
			{
				"node 1" : "%56",
				"node 2" : "%52"

			},
			{
				"node 1" : "%56",
				"node 2" : "%53"

			},
			{
				"node 1" : "%45",
				"node 2" : "%46"

			},
			{
				"node 1" : "%46",
				"node 2" : "%47"

			},
			{
				"node 1" : "%46",
				"node 2" : "%48"

			},
			{
				"node 1" : "%46",
				"node 2" : "%49"

			},
			{
				"node 1" : "%46",
				"node 2" : "%50"

			},
			{
				"node 1" : "%46",
				"node 2" : "%51"

			},
			{
				"node 1" : "%46",
				"node 2" : "%52"

			},
			{
				"node 1" : "%46",
				"node 2" : "%53"

			},
			{
				"node 1" : "%47",
				"node 2" : "%48"

			},
			{
				"node 1" : "%48",
				"node 2" : "%49"

			},
			{
				"node 1" : "%49",
				"node 2" : "%50"

			},
			{
				"node 1" : "%49",
				"node 2" : "%51"

			},
			{
				"node 1" : "%49",
				"node 2" : "%52"

			},
			{
				"node 1" : "%49",
				"node 2" : "%53"

			},
			{
				"node 1" : "%50",
				"node 2" : "%51"

			},
			{
				"node 1" : "%51",
				"node 2" : "%52"

			},
			{
				"node 1" : "%52",
				"node 2" : "%53"

			},
			{
				"node 1" : "%58",
				"node 2" : "%59"

			},
			{
				"node 1" : "%58",
				"node 2" : "%60"

			},
			{
				"node 1" : "%58",
				"node 2" : "%61"

			},
			{
				"node 1" : "%58",
				"node 2" : "%62"

			},
			{
				"node 1" : "%58",
				"node 2" : "%63"

			},
			{
				"node 1" : "%59",
				"node 2" : "%60"

			},
			{
				"node 1" : "%61",
				"node 2" : "%62"

			},
			{
				"node 1" : "%62",
				"node 2" : "%63"

			},
			{
				"node 1" : "%63",
				"node 2" : "%64"

			},
			{
				"node 1" : "%63",
				"node 2" : "%65"

			},
			{
				"node 1" : "%63",
				"node 2" : "%66"

			},
			{
				"node 1" : "%63",
				"node 2" : "%67"

			},
			{
				"node 1" : "%63",
				"node 2" : "%68"

			},
			{
				"node 1" : "%64",
				"node 2" : "%65"

			},
			{
				"node 1" : "%65",
				"node 2" : "%66"

			},
			{
				"node 1" : "%66",
				"node 2" : "%67"

			},
			{
				"node 1" : "%67",
				"node 2" : "%68"

			},
			{
				"node 1" : "%68",
				"node 2" : "%69"

			}
		]
	},
	"double" : 	{
		"nodes" : {
			"%0" : {
				"type" : "label",
				"uses" : [1, 6],
				"uses deepness" : [0, 2]
			},
			"%1" : {
				"type" : "",
				"uses" : [1, 7],
				"uses deepness" : [0, 2]
			},
			"%2" : {
				"type" : "",
				"uses" : [1, 5],
				"uses deepness" : [0, 1]
			},
			"%4" : {
				"type" : "label",
				"uses" : [2, 10, 18, 20],
				"uses deepness" : [0, 2, 2, 2]
			},
			"%10" : {
				"type" : "label",
				"uses" : [4, 5, 6, 14],
				"uses deepness" : [0, 1, 2, 2]
			},
			"%3" : {
				"type" : "",
				"uses" : [4, 5, 6],
				"uses deepness" : [0, 1, 2]
			},
			"%.01" : {
				"type" : "double",
				"uses" : [5, 13, 21],
				"uses deepness" : [1, 2, 2]
			},
			"%9" : {
				"type" : "double",
				"uses" : [5, 13],
				"uses deepness" : [1, 2]
			},
			"%.0" : {
				"type" : "ptr",
				"uses" : [6, 7, 11, 17],
				"uses deepness" : [2, 2, 2, 2]
			},
			"%11" : {
				"type" : "ptr",
				"uses" : [6, 17],
				"uses deepness" : [2, 2]
			},
			"%5" : {
				"type" : "label",
				"uses" : [7, 8],
				"uses deepness" : [2, 2]
			},
			"%6" : {
				"type" : "label",
				"uses" : [8, 16],
				"uses deepness" : [2, 2]
			},
			"%12" : {
				"type" : "label",
				"uses" : [8],
				"uses deepness" : [2]
			},
			"%7" : {
				"type" : "ptr",
				"uses" : [11, 12],
				"uses deepness" : [2, 2]
			},
			"%8" : {
				"type" : "i32",
				"uses" : [12, 13],
				"uses deepness" : [2, 2]
			}
		},
		"edges" : [
			{
				"node 1" : "%0",
				"node 2" : "%1"

			},
			{
				"node 1" : "%0",
				"node 2" : "%2"

			},
			{
				"node 1" : "%0",
				"node 2" : "%4"

			},
			{
				"node 1" : "%0",
				"node 2" : "%10"

			},
			{
				"node 1" : "%0",
				"node 2" : "%3"

			},
			{
				"node 1" : "%0",
				"node 2" : "%.01"

			},
			{
				"node 1" : "%0",
				"node 2" : "%9"

			},
			{
				"node 1" : "%0",
				"node 2" : "%.0"

			},
			{
				"node 1" : "%0",
				"node 2" : "%11"

			},
			{
				"node 1" : "%1",
				"node 2" : "%2"

			},
			{
				"node 1" : "%1",
				"node 2" : "%4"

			},
			{
				"node 1" : "%1",
				"node 2" : "%10"

			},
			{
				"node 1" : "%1",
				"node 2" : "%3"

			},
			{
				"node 1" : "%1",
				"node 2" : "%.01"

			},
			{
				"node 1" : "%1",
				"node 2" : "%9"

			},
			{
				"node 1" : "%1",
				"node 2" : "%.0"

			},
			{
				"node 1" : "%1",
				"node 2" : "%11"

			},
			{
				"node 1" : "%1",
				"node 2" : "%5"

			},
			{
				"node 1" : "%2",
				"node 2" : "%4"

			},
			{
				"node 1" : "%2",
				"node 2" : "%10"

			},
			{
				"node 1" : "%2",
				"node 2" : "%3"

			},
			{
				"node 1" : "%2",
				"node 2" : "%.01"

			},
			{
				"node 1" : "%2",
				"node 2" : "%9"

			},
			{
				"node 1" : "%4",
				"node 2" : "%10"

			},
			{
				"node 1" : "%4",
				"node 2" : "%3"

			},
			{
				"node 1" : "%4",
				"node 2" : "%.01"

			},
			{
				"node 1" : "%4",
				"node 2" : "%9"

			},
			{
				"node 1" : "%4",
				"node 2" : "%.0"

			},
			{
				"node 1" : "%4",
				"node 2" : "%11"

			},
			{
				"node 1" : "%4",
				"node 2" : "%5"

			},
			{
				"node 1" : "%4",
				"node 2" : "%6"

			},
			{
				"node 1" : "%4",
				"node 2" : "%12"

			},
			{
				"node 1" : "%4",
				"node 2" : "%7"

			},
			{
				"node 1" : "%4",
				"node 2" : "%8"

			},
			{
				"node 1" : "%10",
				"node 2" : "%3"

			},
			{
				"node 1" : "%10",
				"node 2" : "%.01"

			},
			{
				"node 1" : "%10",
				"node 2" : "%9"

			},
			{
				"node 1" : "%10",
				"node 2" : "%.0"

			},
			{
				"node 1" : "%10",
				"node 2" : "%11"

			},
			{
				"node 1" : "%10",
				"node 2" : "%5"

			},
			{
				"node 1" : "%10",
				"node 2" : "%6"

			},
			{
				"node 1" : "%10",
				"node 2" : "%12"

			},
			{
				"node 1" : "%10",
				"node 2" : "%7"

			},
			{
				"node 1" : "%10",
				"node 2" : "%8"

			},
			{
				"node 1" : "%3",
				"node 2" : "%.01"

			},
			{
				"node 1" : "%3",
				"node 2" : "%9"

			},
			{
				"node 1" : "%3",
				"node 2" : "%.0"

			},
			{
				"node 1" : "%3",
				"node 2" : "%11"

			},
			{
				"node 1" : "%.01",
				"node 2" : "%9"

			},
			{
				"node 1" : "%.01",
				"node 2" : "%.0"

			},
			{
				"node 1" : "%.01",
				"node 2" : "%11"

			},
			{
				"node 1" : "%.01",
				"node 2" : "%5"

			},
			{
				"node 1" : "%.01",
				"node 2" : "%6"

			},
			{
				"node 1" : "%.01",
				"node 2" : "%12"

			},
			{
				"node 1" : "%.01",
				"node 2" : "%7"

			},
			{
				"node 1" : "%.01",
				"node 2" : "%8"

			},
			{
				"node 1" : "%9",
				"node 2" : "%.0"

			},
			{
				"node 1" : "%9",
				"node 2" : "%11"

			},
			{
				"node 1" : "%9",
				"node 2" : "%5"

			},
			{
				"node 1" : "%9",
				"node 2" : "%6"

			},
			{
				"node 1" : "%9",
				"node 2" : "%12"

			},
			{
				"node 1" : "%9",
				"node 2" : "%7"

			},
			{
				"node 1" : "%9",
				"node 2" : "%8"

			},
			{
				"node 1" : "%.0",
				"node 2" : "%11"

			},
			{
				"node 1" : "%.0",
				"node 2" : "%5"

			},
			{
				"node 1" : "%.0",
				"node 2" : "%6"

			},
			{
				"node 1" : "%.0",
				"node 2" : "%12"

			},
			{
				"node 1" : "%.0",
				"node 2" : "%7"

			},
			{
				"node 1" : "%.0",
				"node 2" : "%8"

			},
			{
				"node 1" : "%11",
				"node 2" : "%5"

			},
			{
				"node 1" : "%11",
				"node 2" : "%6"

			},
			{
				"node 1" : "%11",
				"node 2" : "%12"

			},
			{
				"node 1" : "%11",
				"node 2" : "%7"

			},
			{
				"node 1" : "%11",
				"node 2" : "%8"

			},
			{
				"node 1" : "%5",
				"node 2" : "%6"

			},
			{
				"node 1" : "%5",
				"node 2" : "%12"

			},
			{
				"node 1" : "%6",
				"node 2" : "%12"

			},
			{
				"node 1" : "%6",
				"node 2" : "%7"

			},
			{
				"node 1" : "%6",
				"node 2" : "%8"

			},
			{
				"node 1" : "%7",
				"node 2" : "%8"

			}
		]
	},
	"dereferenceable" : 	{
		"nodes" : {
			"%0" : {
				"type" : "label",
				"uses" : [1, 2, 4, 5],
				"uses deepness" : [0, 0, 0, 0]
			},
			"%1" : {
				"type" : "",
				"uses" : [1, 3],
				"uses deepness" : [0, 0]
			},
			"%3" : {
				"type" : "ptr",
				"uses" : [2, 3],
				"uses deepness" : [0, 0]
			},
			"%4" : {
				"type" : "ptr",
				"uses" : [3, 4],
				"uses deepness" : [0, 0]
			}
		},
		"edges" : [
			{
				"node 1" : "%0",
				"node 2" : "%1"

			},
			{
				"node 1" : "%0",
				"node 2" : "%3"

			},
			{
				"node 1" : "%0",
				"node 2" : "%4"

			},
			{
				"node 1" : "%1",
				"node 2" : "%3"

			},
			{
				"node 1" : "%1",
				"node 2" : "%4"

			},
			{
				"node 1" : "%3",
				"node 2" : "%4"

			}
		]
	},
	"i32" : 	{
		"nodes" : {
			"%0" : {
				"type" : "label",
				"uses" : [1, 2],
				"uses deepness" : [0, 0]
			},
			"%1" : {
				"type" : "",
				"uses" : [1, 2],
				"uses deepness" : [0, 0]
			},
			"%3" : {
				"type" : "i32",
				"uses" : [2, 3],
				"uses deepness" : [0, 0]
			}
		},
		"edges" : [
			{
				"node 1" : "%0",
				"node 2" : "%1"

			},
			{
				"node 1" : "%0",
				"node 2" : "%3"

			},
			{
				"node 1" : "%1",
				"node 2" : "%3"

			}
		]
	}
}