{
	"@_Z3gcdii" : 	{
		"nodes" : {
			"%0" : {
				"type" : "label",
				"uses" : [1, 6, 14],
				"uses deepness" : [0, 0, 0]
			},
			"%1" : {
				"type" : "",
				"uses" : [1, 2, 6, 7],
				"uses deepness" : [0, 0, 0, 0]
			},
			"%3" : {
				"type" : "label",
				"uses" : [2, 3],
				"uses deepness" : [0, 0]
			},
			"%4" : {
				"type" : "label",
				"uses" : [3, 13, 14],
				"uses deepness" : [0, 0, 0]
			},
			"%7" : {
				"type" : "label",
				"uses" : [3, 13, 14],
				"uses deepness" : [0, 0, 0]
			},
			"%2" : {
				"type" : "",
				"uses" : [5, 10],
				"uses deepness" : [0, 0]
			},
			"%5" : {
				"type" : "i32",
				"uses" : [6, 7],
				"uses deepness" : [0, 0]
			},
			"%6" : {
				"type" : "i32",
				"uses" : [7, 14],
				"uses deepness" : [0, 0]
			},
			"%8" : {
				"type" : "label",
				"uses" : [8, 11],
				"uses deepness" : [0, 0]
			},
			"%9" : {
				"type" : "i32",
				"uses" : [14, 15],
				"uses deepness" : [0, 0]
			}
		},
		"edges" : [
			{
				"node 1" : "%0",
				"node 2" : "%1"

			},
			{
				"node 1" : "%0",
				"node 2" : "%3"

			},
			{
				"node 1" : "%0",
				"node 2" : "%4"

			},
			{
				"node 1" : "%0",
				"node 2" : "%7"

			},
			{
				"node 1" : "%0",
				"node 2" : "%2"

			},
			{
				"node 1" : "%0",
				"node 2" : "%5"

			},
			{
				"node 1" : "%0",
				"node 2" : "%6"

			},
			{
				"node 1" : "%0",
				"node 2" : "%8"

			},
			{
				"node 1" : "%0",
				"node 2" : "%9"

			},
			{
				"node 1" : "%1",
				"node 2" : "%3"

			},
			{
				"node 1" : "%1",
				"node 2" : "%4"

			},
			{
				"node 1" : "%1",
				"node 2" : "%7"

			},
			{
				"node 1" : "%1",
				"node 2" : "%2"

			},
			{
				"node 1" : "%1",
				"node 2" : "%5"

			},
			{
				"node 1" : "%1",
				"node 2" : "%6"

			},
			{
				"node 1" : "%3",
				"node 2" : "%4"

			},
			{
				"node 1" : "%3",
				"node 2" : "%7"

			},
			{
				"node 1" : "%4",
				"node 2" : "%7"

			},
			{
				"node 1" : "%4",
				"node 2" : "%2"

			},
			{
				"node 1" : "%4",
				"node 2" : "%5"

			},
			{
				"node 1" : "%4",
				"node 2" : "%6"

			},
			{
				"node 1" : "%4",
				"node 2" : "%8"

			},
			{
				"node 1" : "%4",
				"node 2" : "%9"

			},
			{
				"node 1" : "%7",
				"node 2" : "%2"

			},
			{
				"node 1" : "%7",
				"node 2" : "%5"

			},
			{
				"node 1" : "%7",
				"node 2" : "%6"

			},
			{
				"node 1" : "%7",
				"node 2" : "%8"

			},
			{
				"node 1" : "%7",
				"node 2" : "%9"

			},
			{
				"node 1" : "%2",
				"node 2" : "%5"

			},
			{
				"node 1" : "%2",
				"node 2" : "%6"

			},
			{
				"node 1" : "%2",
				"node 2" : "%8"

			},
			{
				"node 1" : "%5",
				"node 2" : "%6"

			},
			{
				"node 1" : "%6",
				"node 2" : "%8"

			},
			{
				"node 1" : "%6",
				"node 2" : "%9"

			}
		]
	},
	"@_Z3lcmii" : 	{
		"nodes" : {
			"%0" : {
				"type" : "label",
				"uses" : [1, 2, 3],
				"uses deepness" : [0, 0, 0]
			},
			"%1" : {
				"type" : "",
				"uses" : [1, 2, 3],
				"uses deepness" : [0, 0, 0]
			},
			"%3" : {
				"type" : "i32",
				"uses" : [2, 4],
				"uses deepness" : [0, 0]
			},
			"%4" : {
				"type" : "i32",
				"uses" : [3, 4],
				"uses deepness" : [0, 0]
			},
			"%5" : {
				"type" : "i32",
				"uses" : [4, 5],
				"uses deepness" : [0, 0]
			}
		},
		"edges" : [
			{
				"node 1" : "%0",
				"node 2" : "%1"

			},
			{
				"node 1" : "%0",
				"node 2" : "%3"

			},
			{
				"node 1" : "%0",
				"node 2" : "%4"

			},
			{
				"node 1" : "%1",
				"node 2" : "%3"

			},
			{
				"node 1" : "%1",
				"node 2" : "%4"

			},
			{
				"node 1" : "%3",
				"node 2" : "%4"

			},
			{
				"node 1" : "%3",
				"node 2" : "%5"

			},
			{
				"node 1" : "%4",
				"node 2" : "%5"

			}
		]
	},
	"@main" : 	{
		"nodes" : {
			"%1" : {
				"type" : "i64",
				"uses" : [2, 30, 35, 49, 58, 77, 80, 102, 106, 120, 156],
				"uses deepness" : [0, 1, 1, 2, 2, 2, 2, 4, 4, 4, 4]
			},
			"%2" : {
				"type" : "ptr",
				"uses" : [3, 29, 30, 34, 73],
				"uses deepness" : [0, 1, 1, 1, 2]
			},
			"%3" : {
				"type" : "ptr",
				"uses" : [4, 78, 83],
				"uses deepness" : [0, 2, 2]
			},
			"%4" : {
				"type" : "ptr",
				"uses" : [5, 81, 85],
				"uses deepness" : [0, 2, 2]
			},
			"%5" : {
				"type" : "ptr",
				"uses" : [6],
				"uses deepness" : [0]
			},
			"%6" : {
				"type" : "label",
				"uses" : [7, 15, 23, 25],
				"uses deepness" : [0, 1, 1, 1]
			},
			"%13" : {
				"type" : "label",
				"uses" : [9, 10, 19],
				"uses deepness" : [0, 1, 1]
			},
			"%0" : {
				"type" : "label",
				"uses" : [9, 10],
				"uses deepness" : [0, 1]
			},
			"%.0" : {
				"type" : "i32",
				"uses" : [10, 12, 16, 22],
				"uses deepness" : [1, 1, 1, 1]
			},
			"%14" : {
				"type" : "i32",
				"uses" : [10, 22],
				"uses deepness" : [1, 1]
			},
			"%7" : {
				"type" : "ptr",
				"uses" : [11, 12],
				"uses deepness" : [1, 1]
			},
			"%8" : {
				"type" : "label",
				"uses" : [12, 13],
				"uses deepness" : [1, 1]
			},
			"%9" : {
				"type" : "label",
				"uses" : [13, 21],
				"uses deepness" : [1, 1]
			},
			"%15" : {
				"type" : "label",
				"uses" : [13, 33, 68],
				"uses deepness" : [1, 1, 2]
			},
			"%10" : {
				"type" : "i32",
				"uses" : [16, 17],
				"uses deepness" : [1, 1]
			},
			"%11" : {
				"type" : "ptr",
				"uses" : [17, 18],
				"uses deepness" : [1, 1]
			},
			"%12" : {
				"type" : "ptr",
				"uses" : [18],
				"uses deepness" : [1]
			},
			"%16" : {
				"type" : "ptr",
				"uses" : [26, 27],
				"uses deepness" : [1, 1]
			},
			"%17" : {
				"type" : "i32",
				"uses" : [27, 28],
				"uses deepness" : [1, 1]
			},
			"%18" : {
				"type" : "i32",
				"uses" : [28, 30],
				"uses deepness" : [1, 1]
			},
			"%19" : {
				"type" : "label",
				"uses" : [31, 39, 40],
				"uses deepness" : [1, 1, 2]
			},
			"%42" : {
				"type" : "label",
				"uses" : [31, 159, 160, 161],
				"uses deepness" : [1, 4, 5, 6]
			},
			"%20" : {
				"type" : "ptr",
				"uses" : [35, 36],
				"uses deepness" : [1, 1]
			},
			"%21" : {
				"type" : "label",
				"uses" : [37, 46, 66, 76],
				"uses deepness" : [1, 2, 2, 2]
			},
			"%40" : {
				"type" : "label",
				"uses" : [39, 40, 62],
				"uses deepness" : [1, 2, 2]
			},
			"%.03" : {
				"type" : "i32",
				"uses" : [40, 43, 47, 51, 57, 65],
				"uses deepness" : [2, 2, 2, 2, 2, 2]
			},
			"%41" : {
				"type" : "i32",
				"uses" : [40, 65],
				"uses deepness" : [2, 2]
			},
			"%22" : {
				"type" : "ptr",
				"uses" : [41, 42],
				"uses deepness" : [2, 2]
			},
			"%23" : {
				"type" : "i32",
				"uses" : [42, 43],
				"uses deepness" : [2, 2]
			},
			"%24" : {
				"type" : "label",
				"uses" : [43, 44],
				"uses deepness" : [2, 2]
			},
			"%25" : {
				"type" : "label",
				"uses" : [44, 64],
				"uses deepness" : [2, 2]
			},
			"%46" : {
				"type" : "label",
				"uses" : [44, 90, 115],
				"uses deepness" : [2, 2, 4]
			},
			"%26" : {
				"type" : "i32",
				"uses" : [47, 48],
				"uses deepness" : [2, 2]
			},
			"%27" : {
				"type" : "i32",
				"uses" : [48, 49],
				"uses deepness" : [2, 2]
			},
			"%28" : {
				"type" : "ptr",
				"uses" : [49, 50],
				"uses deepness" : [2, 2]
			},
			"%29" : {
				"type" : "ptr",
				"uses" : [50, 56],
				"uses deepness" : [2, 2]
			},
			"%30" : {
				"type" : "i32",
				"uses" : [51, 52],
				"uses deepness" : [2, 2]
			},
			"%31" : {
				"type" : "i32",
				"uses" : [52, 53],
				"uses deepness" : [2, 2]
			},
			"%32" : {
				"type" : "ptr",
				"uses" : [53, 54],
				"uses deepness" : [2, 2]
			},
			"%33" : {
				"type" : "ptr",
				"uses" : [54, 55],
				"uses deepness" : [2, 2]
			},
			"%34" : {
				"type" : "i32",
				"uses" : [55, 56],
				"uses deepness" : [2, 2]
			},
			"%35" : {
				"type" : "i64",
				"uses" : [56, 60],
				"uses deepness" : [2, 2]
			},
			"%36" : {
				"type" : "i32",
				"uses" : [57, 58],
				"uses deepness" : [2, 2]
			},
			"%37" : {
				"type" : "ptr",
				"uses" : [58, 59, 61],
				"uses deepness" : [2, 2, 2]
			},
			"%38" : {
				"type" : "ptr",
				"uses" : [59, 60],
				"uses deepness" : [2, 2]
			},
			"%39" : {
				"type" : "ptr",
				"uses" : [60, 61],
				"uses deepness" : [2, 2]
			},
			"%43" : {
				"type" : "i32",
				"uses" : [69, 71, 72],
				"uses deepness" : [2, 2, 2]
			},
			"%44" : {
				"type" : "i32",
				"uses" : [71, 161],
				"uses deepness" : [2, 6]
			},
			"%45" : {
				"type" : "i32",
				"uses" : [72, 160],
				"uses deepness" : [2, 5]
			},
			"%94" : {
				"type" : "label",
				"uses" : [74, 121],
				"uses deepness" : [2, 4]
			},
			"%47" : {
				"type" : "ptr",
				"uses" : [77, 79],
				"uses deepness" : [2, 2]
			},
			"%48" : {
				"type" : "ptr",
				"uses" : [78, 79],
				"uses deepness" : [2, 2]
			},
			"%49" : {
				"type" : "ptr",
				"uses" : [80, 82],
				"uses deepness" : [2, 2]
			},
			"%50" : {
				"type" : "ptr",
				"uses" : [81, 82],
				"uses deepness" : [2, 2]
			},
			"%51" : {
				"type" : "ptr",
				"uses" : [83, 84],
				"uses deepness" : [2, 2]
			},
			"%52" : {
				"type" : "ptr",
				"uses" : [84, 87],
				"uses deepness" : [2, 2]
			},
			"%53" : {
				"type" : "ptr",
				"uses" : [85, 86],
				"uses deepness" : [2, 2]
			},
			"%54" : {
				"type" : "",
				"uses" : [86, 87],
				"uses deepness" : [2, 2]
			},
			"%55" : {
				"type" : "label",
				"uses" : [88, 93, 94, 95],
				"uses deepness" : [2, 2, 3, 4]
			},
			"%70" : {
				"type" : "label",
				"uses" : [88, 149, 153, 159, 160, 161],
				"uses deepness" : [2, 4, 4, 4, 5, 6]
			},
			"%56" : {
				"type" : "label",
				"uses" : [91, 100, 138, 140],
				"uses deepness" : [2, 4, 4, 4]
			},
			"%81" : {
				"type" : "label",
				"uses" : [93, 94, 95, 134],
				"uses deepness" : [2, 3, 4, 4]
			},
			"%.05" : {
				"type" : "i32",
				"uses" : [94, 97, 101, 104, 137],
				"uses deepness" : [3, 4, 4, 4, 4]
			},
			"%82" : {
				"type" : "i32",
				"uses" : [94, 137],
				"uses deepness" : [3, 4]
			},
			"%.04" : {
				"type" : "i64",
				"uses" : [95, 112, 124, 125, 141, 142],
				"uses deepness" : [4, 4, 4, 4, 4, 4]
			},
			"%.1" : {
				"type" : "i64",
				"uses" : [95, 133],
				"uses deepness" : [4, 4]
			},
			"%57" : {
				"type" : "ptr",
				"uses" : [96, 97],
				"uses deepness" : [4, 4]
			},
			"%58" : {
				"type" : "label",
				"uses" : [97, 98],
				"uses deepness" : [4, 4]
			},
			"%59" : {
				"type" : "label",
				"uses" : [98, 111, 123],
				"uses deepness" : [4, 4, 4]
			},
			"%83" : {
				"type" : "label",
				"uses" : [98, 115, 151],
				"uses deepness" : [4, 4, 4]
			},
			"%60" : {
				"type" : "i32",
				"uses" : [101, 102],
				"uses deepness" : [4, 4]
			},
			"%61" : {
				"type" : "ptr",
				"uses" : [102, 103],
				"uses deepness" : [4, 4]
			},
			"%62" : {
				"type" : "ptr",
				"uses" : [103, 108],
				"uses deepness" : [4, 4]
			},
			"%63" : {
				"type" : "i32",
				"uses" : [104, 105],
				"uses deepness" : [4, 4]
			},
			"%64" : {
				"type" : "i32",
				"uses" : [105, 106],
				"uses deepness" : [4, 4]
			},
			"%65" : {
				"type" : "ptr",
				"uses" : [106, 107],
				"uses deepness" : [4, 4]
			},
			"%66" : {
				"type" : "ptr",
				"uses" : [107, 108],
				"uses deepness" : [4, 4]
			},
			"%67" : {
				"type" : "label",
				"uses" : [108, 109],
				"uses deepness" : [4, 4]
			},
			"%68" : {
				"type" : "label",
				"uses" : [109, 132, 133],
				"uses deepness" : [4, 4, 4]
			},
			"%74" : {
				"type" : "label",
				"uses" : [109, 132, 133],
				"uses deepness" : [4, 4, 4]
			},
			"%69" : {
				"type" : "i64",
				"uses" : [112, 133],
				"uses deepness" : [4, 4]
			},
			"%80" : {
				"type" : "label",
				"uses" : [113, 130, 136],
				"uses deepness" : [4, 4, 4]
			},
			"%91" : {
				"type" : "label",
				"uses" : [115, 149, 155],
				"uses deepness" : [4, 4, 4]
			},
			"%71" : {
				"type" : "i32",
				"uses" : [116, 118, 119],
				"uses deepness" : [4, 4, 4]
			},
			"%72" : {
				"type" : "i32",
				"uses" : [118, 161],
				"uses deepness" : [4, 6]
			},
			"%73" : {
				"type" : "i32",
				"uses" : [119, 160],
				"uses deepness" : [4, 5]
			},
			"%75" : {
				"type" : "i64",
				"uses" : [124, 125],
				"uses deepness" : [4, 4]
			},
			"%76" : {
				"type" : "i64",
				"uses" : [125, 126],
				"uses deepness" : [4, 4]
			},
			"%77" : {
				"type" : "i64",
				"uses" : [126, 128],
				"uses deepness" : [4, 4]
			},
			"%78" : {
				"type" : "ptr",
				"uses" : [127, 128],
				"uses deepness" : [4, 4]
			},
			"%79" : {
				"type" : "ptr",
				"uses" : [128, 129],
				"uses deepness" : [4, 4]
			},
			"%84" : {
				"type" : "i64",
				"uses" : [141, 142],
				"uses deepness" : [4, 4]
			},
			"%85" : {
				"type" : "i64",
				"uses" : [142, 143],
				"uses deepness" : [4, 4]
			},
			"%86" : {
				"type" : "i64",
				"uses" : [143, 145],
				"uses deepness" : [4, 4]
			},
			"%87" : {
				"type" : "ptr",
				"uses" : [144, 145],
				"uses deepness" : [4, 4]
			},
			"%88" : {
				"type" : "ptr",
				"uses" : [145, 146],
				"uses deepness" : [4, 4]
			},
			"%89" : {
				"type" : "ptr",
				"uses" : [147, 148],
				"uses deepness" : [4, 4]
			},
			"%90" : {
				"type" : "i64",
				"uses" : [148, 152],
				"uses deepness" : [4, 4]
			},
			"%92" : {
				"type" : "",
				"uses" : [152],
				"uses deepness" : [4]
			},
			"%93" : {
				"type" : "label",
				"uses" : [153],
				"uses deepness" : [4]
			},
			"%.02" : {
				"type" : "i32",
				"uses" : [160, 163],
				"uses deepness" : [5, 6]
			},
			"%.01" : {
				"type" : "ptr",
				"uses" : [161, 162],
				"uses deepness" : [6, 6]
			},
			"%95" : {
				"type" : "i32",
				"uses" : [162, 163],
				"uses deepness" : [6, 6]
			},
			"%96" : {
				"type" : "i32",
				"uses" : [163, 164],
				"uses deepness" : [6, 6]
			}
		},
		"edges" : [
			{
				"node 1" : "%1",
				"node 2" : "%2"

			},
			{
				"node 1" : "%1",
				"node 2" : "%3"

			},
			{
				"node 1" : "%1",
				"node 2" : "%4"

			},
			{
				"node 1" : "%1",
				"node 2" : "%5"

			},
			{
				"node 1" : "%1",
				"node 2" : "%6"

			},
			{
				"node 1" : "%1",
				"node 2" : "%13"

			},
			{
				"node 1" : "%1",
				"node 2" : "%0"

			},
			{
				"node 1" : "%1",
				"node 2" : "%.0"

			},
			{
				"node 1" : "%1",
				"node 2" : "%14"

			},
			{
				"node 1" : "%1",
				"node 2" : "%7"

			},
			{
				"node 1" : "%1",
				"node 2" : "%8"

			},
			{
				"node 1" : "%1",
				"node 2" : "%9"

			},
			{
				"node 1" : "%1",
				"node 2" : "%15"

			},
			{
				"node 1" : "%1",
				"node 2" : "%10"

			},
			{
				"node 1" : "%1",
				"node 2" : "%11"

			},
			{
				"node 1" : "%1",
				"node 2" : "%12"

			},
			{
				"node 1" : "%1",
				"node 2" : "%16"

			},
			{
				"node 1" : "%1",
				"node 2" : "%17"

			},
			{
				"node 1" : "%1",
				"node 2" : "%18"

			},
			{
				"node 1" : "%1",
				"node 2" : "%19"

			},
			{
				"node 1" : "%1",
				"node 2" : "%42"

			},
			{
				"node 1" : "%1",
				"node 2" : "%20"

			},
			{
				"node 1" : "%1",
				"node 2" : "%21"

			},
			{
				"node 1" : "%1",
				"node 2" : "%40"

			},
			{
				"node 1" : "%1",
				"node 2" : "%.03"

			},
			{
				"node 1" : "%1",
				"node 2" : "%41"

			},
			{
				"node 1" : "%1",
				"node 2" : "%22"

			},
			{
				"node 1" : "%1",
				"node 2" : "%23"

			},
			{
				"node 1" : "%1",
				"node 2" : "%24"

			},
			{
				"node 1" : "%1",
				"node 2" : "%25"

			},
			{
				"node 1" : "%1",
				"node 2" : "%46"

			},
			{
				"node 1" : "%1",
				"node 2" : "%26"

			},
			{
				"node 1" : "%1",
				"node 2" : "%27"

			},
			{
				"node 1" : "%1",
				"node 2" : "%28"

			},
			{
				"node 1" : "%1",
				"node 2" : "%29"

			},
			{
				"node 1" : "%1",
				"node 2" : "%30"

			},
			{
				"node 1" : "%1",
				"node 2" : "%31"

			},
			{
				"node 1" : "%1",
				"node 2" : "%32"

			},
			{
				"node 1" : "%1",
				"node 2" : "%33"

			},
			{
				"node 1" : "%1",
				"node 2" : "%34"

			},
			{
				"node 1" : "%1",
				"node 2" : "%35"

			},
			{
				"node 1" : "%1",
				"node 2" : "%36"

			},
			{
				"node 1" : "%1",
				"node 2" : "%37"

			},
			{
				"node 1" : "%1",
				"node 2" : "%38"

			},
			{
				"node 1" : "%1",
				"node 2" : "%39"

			},
			{
				"node 1" : "%1",
				"node 2" : "%43"

			},
			{
				"node 1" : "%1",
				"node 2" : "%44"

			},
			{
				"node 1" : "%1",
				"node 2" : "%45"

			},
			{
				"node 1" : "%1",
				"node 2" : "%94"

			},
			{
				"node 1" : "%1",
				"node 2" : "%47"

			},
			{
				"node 1" : "%1",
				"node 2" : "%48"

			},
			{
				"node 1" : "%1",
				"node 2" : "%49"

			},
			{
				"node 1" : "%1",
				"node 2" : "%50"

			},
			{
				"node 1" : "%1",
				"node 2" : "%51"

			},
			{
				"node 1" : "%1",
				"node 2" : "%52"

			},
			{
				"node 1" : "%1",
				"node 2" : "%53"

			},
			{
				"node 1" : "%1",
				"node 2" : "%54"

			},
			{
				"node 1" : "%1",
				"node 2" : "%55"

			},
			{
				"node 1" : "%1",
				"node 2" : "%70"

			},
			{
				"node 1" : "%1",
				"node 2" : "%56"

			},
			{
				"node 1" : "%1",
				"node 2" : "%81"

			},
			{
				"node 1" : "%1",
				"node 2" : "%.05"

			},
			{
				"node 1" : "%1",
				"node 2" : "%82"

			},
			{
				"node 1" : "%1",
				"node 2" : "%.04"

			},
			{
				"node 1" : "%1",
				"node 2" : "%.1"

			},
			{
				"node 1" : "%1",
				"node 2" : "%57"

			},
			{
				"node 1" : "%1",
				"node 2" : "%58"

			},
			{
				"node 1" : "%1",
				"node 2" : "%59"

			},
			{
				"node 1" : "%1",
				"node 2" : "%83"

			},
			{
				"node 1" : "%1",
				"node 2" : "%60"

			},
			{
				"node 1" : "%1",
				"node 2" : "%61"

			},
			{
				"node 1" : "%1",
				"node 2" : "%62"

			},
			{
				"node 1" : "%1",
				"node 2" : "%63"

			},
			{
				"node 1" : "%1",
				"node 2" : "%64"

			},
			{
				"node 1" : "%1",
				"node 2" : "%65"

			},
			{
				"node 1" : "%1",
				"node 2" : "%66"

			},
			{
				"node 1" : "%1",
				"node 2" : "%67"

			},
			{
				"node 1" : "%1",
				"node 2" : "%68"

			},
			{
				"node 1" : "%1",
				"node 2" : "%74"

			},
			{
				"node 1" : "%1",
				"node 2" : "%69"

			},
			{
				"node 1" : "%1",
				"node 2" : "%80"

			},
			{
				"node 1" : "%1",
				"node 2" : "%91"

			},
			{
				"node 1" : "%1",
				"node 2" : "%71"

			},
			{
				"node 1" : "%1",
				"node 2" : "%72"

			},
			{
				"node 1" : "%1",
				"node 2" : "%73"

			},
			{
				"node 1" : "%1",
				"node 2" : "%75"

			},
			{
				"node 1" : "%1",
				"node 2" : "%76"

			},
			{
				"node 1" : "%1",
				"node 2" : "%77"

			},
			{
				"node 1" : "%1",
				"node 2" : "%78"

			},
			{
				"node 1" : "%1",
				"node 2" : "%79"

			},
			{
				"node 1" : "%1",
				"node 2" : "%84"

			},
			{
				"node 1" : "%1",
				"node 2" : "%85"

			},
			{
				"node 1" : "%1",
				"node 2" : "%86"

			},
			{
				"node 1" : "%1",
				"node 2" : "%87"

			},
			{
				"node 1" : "%1",
				"node 2" : "%88"

			},
			{
				"node 1" : "%1",
				"node 2" : "%89"

			},
			{
				"node 1" : "%1",
				"node 2" : "%90"

			},
			{
				"node 1" : "%1",
				"node 2" : "%92"

			},
			{
				"node 1" : "%1",
				"node 2" : "%93"

			},
			{
				"node 1" : "%2",
				"node 2" : "%3"

			},
			{
				"node 1" : "%2",
				"node 2" : "%4"

			},
			{
				"node 1" : "%2",
				"node 2" : "%5"

			},
			{
				"node 1" : "%2",
				"node 2" : "%6"

			},
			{
				"node 1" : "%2",
				"node 2" : "%13"

			},
			{
				"node 1" : "%2",
				"node 2" : "%0"

			},
			{
				"node 1" : "%2",
				"node 2" : "%.0"

			},
			{
				"node 1" : "%2",
				"node 2" : "%14"

			},
			{
				"node 1" : "%2",
				"node 2" : "%7"

			},
			{
				"node 1" : "%2",
				"node 2" : "%8"

			},
			{
				"node 1" : "%2",
				"node 2" : "%9"

			},
			{
				"node 1" : "%2",
				"node 2" : "%15"

			},
			{
				"node 1" : "%2",
				"node 2" : "%10"

			},
			{
				"node 1" : "%2",
				"node 2" : "%11"

			},
			{
				"node 1" : "%2",
				"node 2" : "%12"

			},
			{
				"node 1" : "%2",
				"node 2" : "%16"

			},
			{
				"node 1" : "%2",
				"node 2" : "%17"

			},
			{
				"node 1" : "%2",
				"node 2" : "%18"

			},
			{
				"node 1" : "%2",
				"node 2" : "%19"

			},
			{
				"node 1" : "%2",
				"node 2" : "%42"

			},
			{
				"node 1" : "%2",
				"node 2" : "%20"

			},
			{
				"node 1" : "%2",
				"node 2" : "%21"

			},
			{
				"node 1" : "%2",
				"node 2" : "%40"

			},
			{
				"node 1" : "%2",
				"node 2" : "%.03"

			},
			{
				"node 1" : "%2",
				"node 2" : "%41"

			},
			{
				"node 1" : "%2",
				"node 2" : "%22"

			},
			{
				"node 1" : "%2",
				"node 2" : "%23"

			},
			{
				"node 1" : "%2",
				"node 2" : "%24"

			},
			{
				"node 1" : "%2",
				"node 2" : "%25"

			},
			{
				"node 1" : "%2",
				"node 2" : "%46"

			},
			{
				"node 1" : "%2",
				"node 2" : "%26"

			},
			{
				"node 1" : "%2",
				"node 2" : "%27"

			},
			{
				"node 1" : "%2",
				"node 2" : "%28"

			},
			{
				"node 1" : "%2",
				"node 2" : "%29"

			},
			{
				"node 1" : "%2",
				"node 2" : "%30"

			},
			{
				"node 1" : "%2",
				"node 2" : "%31"

			},
			{
				"node 1" : "%2",
				"node 2" : "%32"

			},
			{
				"node 1" : "%2",
				"node 2" : "%33"

			},
			{
				"node 1" : "%2",
				"node 2" : "%34"

			},
			{
				"node 1" : "%2",
				"node 2" : "%35"

			},
			{
				"node 1" : "%2",
				"node 2" : "%36"

			},
			{
				"node 1" : "%2",
				"node 2" : "%37"

			},
			{
				"node 1" : "%2",
				"node 2" : "%38"

			},
			{
				"node 1" : "%2",
				"node 2" : "%39"

			},
			{
				"node 1" : "%2",
				"node 2" : "%43"

			},
			{
				"node 1" : "%2",
				"node 2" : "%44"

			},
			{
				"node 1" : "%2",
				"node 2" : "%45"

			},
			{
				"node 1" : "%3",
				"node 2" : "%4"

			},
			{
				"node 1" : "%3",
				"node 2" : "%5"

			},
			{
				"node 1" : "%3",
				"node 2" : "%6"

			},
			{
				"node 1" : "%3",
				"node 2" : "%13"

			},
			{
				"node 1" : "%3",
				"node 2" : "%0"

			},
			{
				"node 1" : "%3",
				"node 2" : "%.0"

			},
			{
				"node 1" : "%3",
				"node 2" : "%14"

			},
			{
				"node 1" : "%3",
				"node 2" : "%7"

			},
			{
				"node 1" : "%3",
				"node 2" : "%8"

			},
			{
				"node 1" : "%3",
				"node 2" : "%9"

			},
			{
				"node 1" : "%3",
				"node 2" : "%15"

			},
			{
				"node 1" : "%3",
				"node 2" : "%10"

			},
			{
				"node 1" : "%3",
				"node 2" : "%11"

			},
			{
				"node 1" : "%3",
				"node 2" : "%12"

			},
			{
				"node 1" : "%3",
				"node 2" : "%16"

			},
			{
				"node 1" : "%3",
				"node 2" : "%17"

			},
			{
				"node 1" : "%3",
				"node 2" : "%18"

			},
			{
				"node 1" : "%3",
				"node 2" : "%19"

			},
			{
				"node 1" : "%3",
				"node 2" : "%42"

			},
			{
				"node 1" : "%3",
				"node 2" : "%20"

			},
			{
				"node 1" : "%3",
				"node 2" : "%21"

			},
			{
				"node 1" : "%3",
				"node 2" : "%40"

			},
			{
				"node 1" : "%3",
				"node 2" : "%.03"

			},
			{
				"node 1" : "%3",
				"node 2" : "%41"

			},
			{
				"node 1" : "%3",
				"node 2" : "%22"

			},
			{
				"node 1" : "%3",
				"node 2" : "%23"

			},
			{
				"node 1" : "%3",
				"node 2" : "%24"

			},
			{
				"node 1" : "%3",
				"node 2" : "%25"

			},
			{
				"node 1" : "%3",
				"node 2" : "%46"

			},
			{
				"node 1" : "%3",
				"node 2" : "%26"

			},
			{
				"node 1" : "%3",
				"node 2" : "%27"

			},
			{
				"node 1" : "%3",
				"node 2" : "%28"

			},
			{
				"node 1" : "%3",
				"node 2" : "%29"

			},
			{
				"node 1" : "%3",
				"node 2" : "%30"

			},
			{
				"node 1" : "%3",
				"node 2" : "%31"

			},
			{
				"node 1" : "%3",
				"node 2" : "%32"

			},
			{
				"node 1" : "%3",
				"node 2" : "%33"

			},
			{
				"node 1" : "%3",
				"node 2" : "%34"

			},
			{
				"node 1" : "%3",
				"node 2" : "%35"

			},
			{
				"node 1" : "%3",
				"node 2" : "%36"

			},
			{
				"node 1" : "%3",
				"node 2" : "%37"

			},
			{
				"node 1" : "%3",
				"node 2" : "%38"

			},
			{
				"node 1" : "%3",
				"node 2" : "%39"

			},
			{
				"node 1" : "%3",
				"node 2" : "%43"

			},
			{
				"node 1" : "%3",
				"node 2" : "%44"

			},
			{
				"node 1" : "%3",
				"node 2" : "%45"

			},
			{
				"node 1" : "%3",
				"node 2" : "%94"

			},
			{
				"node 1" : "%3",
				"node 2" : "%47"

			},
			{
				"node 1" : "%3",
				"node 2" : "%48"

			},
			{
				"node 1" : "%3",
				"node 2" : "%49"

			},
			{
				"node 1" : "%3",
				"node 2" : "%50"

			},
			{
				"node 1" : "%3",
				"node 2" : "%51"

			},
			{
				"node 1" : "%4",
				"node 2" : "%5"

			},
			{
				"node 1" : "%4",
				"node 2" : "%6"

			},
			{
				"node 1" : "%4",
				"node 2" : "%13"

			},
			{
				"node 1" : "%4",
				"node 2" : "%0"

			},
			{
				"node 1" : "%4",
				"node 2" : "%.0"

			},
			{
				"node 1" : "%4",
				"node 2" : "%14"

			},
			{
				"node 1" : "%4",
				"node 2" : "%7"

			},
			{
				"node 1" : "%4",
				"node 2" : "%8"

			},
			{
				"node 1" : "%4",
				"node 2" : "%9"

			},
			{
				"node 1" : "%4",
				"node 2" : "%15"

			},
			{
				"node 1" : "%4",
				"node 2" : "%10"

			},
			{
				"node 1" : "%4",
				"node 2" : "%11"

			},
			{
				"node 1" : "%4",
				"node 2" : "%12"

			},
			{
				"node 1" : "%4",
				"node 2" : "%16"

			},
			{
				"node 1" : "%4",
				"node 2" : "%17"

			},
			{
				"node 1" : "%4",
				"node 2" : "%18"

			},
			{
				"node 1" : "%4",
				"node 2" : "%19"

			},
			{
				"node 1" : "%4",
				"node 2" : "%42"

			},
			{
				"node 1" : "%4",
				"node 2" : "%20"

			},
			{
				"node 1" : "%4",
				"node 2" : "%21"

			},
			{
				"node 1" : "%4",
				"node 2" : "%40"

			},
			{
				"node 1" : "%4",
				"node 2" : "%.03"

			},
			{
				"node 1" : "%4",
				"node 2" : "%41"

			},
			{
				"node 1" : "%4",
				"node 2" : "%22"

			},
			{
				"node 1" : "%4",
				"node 2" : "%23"

			},
			{
				"node 1" : "%4",
				"node 2" : "%24"

			},
			{
				"node 1" : "%4",
				"node 2" : "%25"

			},
			{
				"node 1" : "%4",
				"node 2" : "%46"

			},
			{
				"node 1" : "%4",
				"node 2" : "%26"

			},
			{
				"node 1" : "%4",
				"node 2" : "%27"

			},
			{
				"node 1" : "%4",
				"node 2" : "%28"

			},
			{
				"node 1" : "%4",
				"node 2" : "%29"

			},
			{
				"node 1" : "%4",
				"node 2" : "%30"

			},
			{
				"node 1" : "%4",
				"node 2" : "%31"

			},
			{
				"node 1" : "%4",
				"node 2" : "%32"

			},
			{
				"node 1" : "%4",
				"node 2" : "%33"

			},
			{
				"node 1" : "%4",
				"node 2" : "%34"

			},
			{
				"node 1" : "%4",
				"node 2" : "%35"

			},
			{
				"node 1" : "%4",
				"node 2" : "%36"

			},
			{
				"node 1" : "%4",
				"node 2" : "%37"

			},
			{
				"node 1" : "%4",
				"node 2" : "%38"

			},
			{
				"node 1" : "%4",
				"node 2" : "%39"

			},
			{
				"node 1" : "%4",
				"node 2" : "%43"

			},
			{
				"node 1" : "%4",
				"node 2" : "%44"

			},
			{
				"node 1" : "%4",
				"node 2" : "%45"

			},
			{
				"node 1" : "%4",
				"node 2" : "%94"

			},
			{
				"node 1" : "%4",
				"node 2" : "%47"

			},
			{
				"node 1" : "%4",
				"node 2" : "%48"

			},
			{
				"node 1" : "%4",
				"node 2" : "%49"

			},
			{
				"node 1" : "%4",
				"node 2" : "%50"

			},
			{
				"node 1" : "%4",
				"node 2" : "%51"

			},
			{
				"node 1" : "%4",
				"node 2" : "%52"

			},
			{
				"node 1" : "%4",
				"node 2" : "%53"

			},
			{
				"node 1" : "%6",
				"node 2" : "%13"

			},
			{
				"node 1" : "%6",
				"node 2" : "%0"

			},
			{
				"node 1" : "%6",
				"node 2" : "%.0"

			},
			{
				"node 1" : "%6",
				"node 2" : "%14"

			},
			{
				"node 1" : "%6",
				"node 2" : "%7"

			},
			{
				"node 1" : "%6",
				"node 2" : "%8"

			},
			{
				"node 1" : "%6",
				"node 2" : "%9"

			},
			{
				"node 1" : "%6",
				"node 2" : "%15"

			},
			{
				"node 1" : "%6",
				"node 2" : "%10"

			},
			{
				"node 1" : "%6",
				"node 2" : "%11"

			},
			{
				"node 1" : "%6",
				"node 2" : "%12"

			},
			{
				"node 1" : "%13",
				"node 2" : "%0"

			},
			{
				"node 1" : "%13",
				"node 2" : "%.0"

			},
			{
				"node 1" : "%13",
				"node 2" : "%14"

			},
			{
				"node 1" : "%13",
				"node 2" : "%7"

			},
			{
				"node 1" : "%13",
				"node 2" : "%8"

			},
			{
				"node 1" : "%13",
				"node 2" : "%9"

			},
			{
				"node 1" : "%13",
				"node 2" : "%15"

			},
			{
				"node 1" : "%13",
				"node 2" : "%10"

			},
			{
				"node 1" : "%13",
				"node 2" : "%11"

			},
			{
				"node 1" : "%13",
				"node 2" : "%12"

			},
			{
				"node 1" : "%0",
				"node 2" : "%.0"

			},
			{
				"node 1" : "%0",
				"node 2" : "%14"

			},
			{
				"node 1" : "%.0",
				"node 2" : "%14"

			},
			{
				"node 1" : "%.0",
				"node 2" : "%7"

			},
			{
				"node 1" : "%.0",
				"node 2" : "%8"

			},
			{
				"node 1" : "%.0",
				"node 2" : "%9"

			},
			{
				"node 1" : "%.0",
				"node 2" : "%15"

			},
			{
				"node 1" : "%.0",
				"node 2" : "%10"

			},
			{
				"node 1" : "%.0",
				"node 2" : "%11"

			},
			{
				"node 1" : "%.0",
				"node 2" : "%12"

			},
			{
				"node 1" : "%14",
				"node 2" : "%7"

			},
			{
				"node 1" : "%14",
				"node 2" : "%8"

			},
			{
				"node 1" : "%14",
				"node 2" : "%9"

			},
			{
				"node 1" : "%14",
				"node 2" : "%15"

			},
			{
				"node 1" : "%14",
				"node 2" : "%10"

			},
			{
				"node 1" : "%14",
				"node 2" : "%11"

			},
			{
				"node 1" : "%14",
				"node 2" : "%12"

			},
			{
				"node 1" : "%7",
				"node 2" : "%8"

			},
			{
				"node 1" : "%8",
				"node 2" : "%9"

			},
			{
				"node 1" : "%8",
				"node 2" : "%15"

			},
			{
				"node 1" : "%9",
				"node 2" : "%15"

			},
			{
				"node 1" : "%9",
				"node 2" : "%10"

			},
			{
				"node 1" : "%9",
				"node 2" : "%11"

			},
			{
				"node 1" : "%9",
				"node 2" : "%12"

			},
			{
				"node 1" : "%15",
				"node 2" : "%10"

			},
			{
				"node 1" : "%15",
				"node 2" : "%11"

			},
			{
				"node 1" : "%15",
				"node 2" : "%12"

			},
			{
				"node 1" : "%15",
				"node 2" : "%16"

			},
			{
				"node 1" : "%15",
				"node 2" : "%17"

			},
			{
				"node 1" : "%15",
				"node 2" : "%18"

			},
			{
				"node 1" : "%15",
				"node 2" : "%19"

			},
			{
				"node 1" : "%15",
				"node 2" : "%42"

			},
			{
				"node 1" : "%15",
				"node 2" : "%20"

			},
			{
				"node 1" : "%15",
				"node 2" : "%21"

			},
			{
				"node 1" : "%15",
				"node 2" : "%40"

			},
			{
				"node 1" : "%15",
				"node 2" : "%.03"

			},
			{
				"node 1" : "%15",
				"node 2" : "%41"

			},
			{
				"node 1" : "%15",
				"node 2" : "%22"

			},
			{
				"node 1" : "%15",
				"node 2" : "%23"

			},
			{
				"node 1" : "%15",
				"node 2" : "%24"

			},
			{
				"node 1" : "%15",
				"node 2" : "%25"

			},
			{
				"node 1" : "%15",
				"node 2" : "%46"

			},
			{
				"node 1" : "%15",
				"node 2" : "%26"

			},
			{
				"node 1" : "%15",
				"node 2" : "%27"

			},
			{
				"node 1" : "%15",
				"node 2" : "%28"

			},
			{
				"node 1" : "%15",
				"node 2" : "%29"

			},
			{
				"node 1" : "%15",
				"node 2" : "%30"

			},
			{
				"node 1" : "%15",
				"node 2" : "%31"

			},
			{
				"node 1" : "%15",
				"node 2" : "%32"

			},
			{
				"node 1" : "%15",
				"node 2" : "%33"

			},
			{
				"node 1" : "%15",
				"node 2" : "%34"

			},
			{
				"node 1" : "%15",
				"node 2" : "%35"

			},
			{
				"node 1" : "%15",
				"node 2" : "%36"

			},
			{
				"node 1" : "%15",
				"node 2" : "%37"

			},
			{
				"node 1" : "%15",
				"node 2" : "%38"

			},
			{
				"node 1" : "%15",
				"node 2" : "%39"

			},
			{
				"node 1" : "%10",
				"node 2" : "%11"

			},
			{
				"node 1" : "%11",
				"node 2" : "%12"

			},
			{
				"node 1" : "%16",
				"node 2" : "%17"

			},
			{
				"node 1" : "%17",
				"node 2" : "%18"

			},
			{
				"node 1" : "%19",
				"node 2" : "%42"

			},
			{
				"node 1" : "%19",
				"node 2" : "%20"

			},
			{
				"node 1" : "%19",
				"node 2" : "%21"

			},
			{
				"node 1" : "%19",
				"node 2" : "%40"

			},
			{
				"node 1" : "%19",
				"node 2" : "%.03"

			},
			{
				"node 1" : "%19",
				"node 2" : "%41"

			},
			{
				"node 1" : "%42",
				"node 2" : "%20"

			},
			{
				"node 1" : "%42",
				"node 2" : "%21"

			},
			{
				"node 1" : "%42",
				"node 2" : "%40"

			},
			{
				"node 1" : "%42",
				"node 2" : "%.03"

			},
			{
				"node 1" : "%42",
				"node 2" : "%41"

			},
			{
				"node 1" : "%42",
				"node 2" : "%22"

			},
			{
				"node 1" : "%42",
				"node 2" : "%23"

			},
			{
				"node 1" : "%42",
				"node 2" : "%24"

			},
			{
				"node 1" : "%42",
				"node 2" : "%25"

			},
			{
				"node 1" : "%42",
				"node 2" : "%46"

			},
			{
				"node 1" : "%42",
				"node 2" : "%26"

			},
			{
				"node 1" : "%42",
				"node 2" : "%27"

			},
			{
				"node 1" : "%42",
				"node 2" : "%28"

			},
			{
				"node 1" : "%42",
				"node 2" : "%29"

			},
			{
				"node 1" : "%42",
				"node 2" : "%30"

			},
			{
				"node 1" : "%42",
				"node 2" : "%31"

			},
			{
				"node 1" : "%42",
				"node 2" : "%32"

			},
			{
				"node 1" : "%42",
				"node 2" : "%33"

			},
			{
				"node 1" : "%42",
				"node 2" : "%34"

			},
			{
				"node 1" : "%42",
				"node 2" : "%35"

			},
			{
				"node 1" : "%42",
				"node 2" : "%36"

			},
			{
				"node 1" : "%42",
				"node 2" : "%37"

			},
			{
				"node 1" : "%42",
				"node 2" : "%38"

			},
			{
				"node 1" : "%42",
				"node 2" : "%39"

			},
			{
				"node 1" : "%42",
				"node 2" : "%43"

			},
			{
				"node 1" : "%42",
				"node 2" : "%44"

			},
			{
				"node 1" : "%42",
				"node 2" : "%45"

			},
			{
				"node 1" : "%42",
				"node 2" : "%94"

			},
			{
				"node 1" : "%42",
				"node 2" : "%47"

			},
			{
				"node 1" : "%42",
				"node 2" : "%48"

			},
			{
				"node 1" : "%42",
				"node 2" : "%49"

			},
			{
				"node 1" : "%42",
				"node 2" : "%50"

			},
			{
				"node 1" : "%42",
				"node 2" : "%51"

			},
			{
				"node 1" : "%42",
				"node 2" : "%52"

			},
			{
				"node 1" : "%42",
				"node 2" : "%53"

			},
			{
				"node 1" : "%42",
				"node 2" : "%54"

			},
			{
				"node 1" : "%42",
				"node 2" : "%55"

			},
			{
				"node 1" : "%42",
				"node 2" : "%70"

			},
			{
				"node 1" : "%42",
				"node 2" : "%56"

			},
			{
				"node 1" : "%42",
				"node 2" : "%81"

			},
			{
				"node 1" : "%42",
				"node 2" : "%.05"

			},
			{
				"node 1" : "%42",
				"node 2" : "%82"

			},
			{
				"node 1" : "%42",
				"node 2" : "%.04"

			},
			{
				"node 1" : "%42",
				"node 2" : "%.1"

			},
			{
				"node 1" : "%42",
				"node 2" : "%57"

			},
			{
				"node 1" : "%42",
				"node 2" : "%58"

			},
			{
				"node 1" : "%42",
				"node 2" : "%59"

			},
			{
				"node 1" : "%42",
				"node 2" : "%83"

			},
			{
				"node 1" : "%42",
				"node 2" : "%60"

			},
			{
				"node 1" : "%42",
				"node 2" : "%61"

			},
			{
				"node 1" : "%42",
				"node 2" : "%62"

			},
			{
				"node 1" : "%42",
				"node 2" : "%63"

			},
			{
				"node 1" : "%42",
				"node 2" : "%64"

			},
			{
				"node 1" : "%42",
				"node 2" : "%65"

			},
			{
				"node 1" : "%42",
				"node 2" : "%66"

			},
			{
				"node 1" : "%42",
				"node 2" : "%67"

			},
			{
				"node 1" : "%42",
				"node 2" : "%68"

			},
			{
				"node 1" : "%42",
				"node 2" : "%74"

			},
			{
				"node 1" : "%42",
				"node 2" : "%69"

			},
			{
				"node 1" : "%42",
				"node 2" : "%80"

			},
			{
				"node 1" : "%42",
				"node 2" : "%91"

			},
			{
				"node 1" : "%42",
				"node 2" : "%71"

			},
			{
				"node 1" : "%42",
				"node 2" : "%72"

			},
			{
				"node 1" : "%42",
				"node 2" : "%73"

			},
			{
				"node 1" : "%42",
				"node 2" : "%75"

			},
			{
				"node 1" : "%42",
				"node 2" : "%76"

			},
			{
				"node 1" : "%42",
				"node 2" : "%77"

			},
			{
				"node 1" : "%42",
				"node 2" : "%78"

			},
			{
				"node 1" : "%42",
				"node 2" : "%79"

			},
			{
				"node 1" : "%42",
				"node 2" : "%84"

			},
			{
				"node 1" : "%42",
				"node 2" : "%85"

			},
			{
				"node 1" : "%42",
				"node 2" : "%86"

			},
			{
				"node 1" : "%42",
				"node 2" : "%87"

			},
			{
				"node 1" : "%42",
				"node 2" : "%88"

			},
			{
				"node 1" : "%42",
				"node 2" : "%89"

			},
			{
				"node 1" : "%42",
				"node 2" : "%90"

			},
			{
				"node 1" : "%42",
				"node 2" : "%92"

			},
			{
				"node 1" : "%42",
				"node 2" : "%93"

			},
			{
				"node 1" : "%42",
				"node 2" : "%.02"

			},
			{
				"node 1" : "%42",
				"node 2" : "%.01"

			},
			{
				"node 1" : "%21",
				"node 2" : "%40"

			},
			{
				"node 1" : "%21",
				"node 2" : "%.03"

			},
			{
				"node 1" : "%21",
				"node 2" : "%41"

			},
			{
				"node 1" : "%21",
				"node 2" : "%22"

			},
			{
				"node 1" : "%21",
				"node 2" : "%23"

			},
			{
				"node 1" : "%21",
				"node 2" : "%24"

			},
			{
				"node 1" : "%21",
				"node 2" : "%25"

			},
			{
				"node 1" : "%21",
				"node 2" : "%46"

			},
			{
				"node 1" : "%21",
				"node 2" : "%26"

			},
			{
				"node 1" : "%21",
				"node 2" : "%27"

			},
			{
				"node 1" : "%21",
				"node 2" : "%28"

			},
			{
				"node 1" : "%21",
				"node 2" : "%29"

			},
			{
				"node 1" : "%21",
				"node 2" : "%30"

			},
			{
				"node 1" : "%21",
				"node 2" : "%31"

			},
			{
				"node 1" : "%21",
				"node 2" : "%32"

			},
			{
				"node 1" : "%21",
				"node 2" : "%33"

			},
			{
				"node 1" : "%21",
				"node 2" : "%34"

			},
			{
				"node 1" : "%21",
				"node 2" : "%35"

			},
			{
				"node 1" : "%21",
				"node 2" : "%36"

			},
			{
				"node 1" : "%21",
				"node 2" : "%37"

			},
			{
				"node 1" : "%21",
				"node 2" : "%38"

			},
			{
				"node 1" : "%21",
				"node 2" : "%39"

			},
			{
				"node 1" : "%21",
				"node 2" : "%43"

			},
			{
				"node 1" : "%21",
				"node 2" : "%44"

			},
			{
				"node 1" : "%21",
				"node 2" : "%45"

			},
			{
				"node 1" : "%21",
				"node 2" : "%94"

			},
			{
				"node 1" : "%40",
				"node 2" : "%.03"

			},
			{
				"node 1" : "%40",
				"node 2" : "%41"

			},
			{
				"node 1" : "%40",
				"node 2" : "%22"

			},
			{
				"node 1" : "%40",
				"node 2" : "%23"

			},
			{
				"node 1" : "%40",
				"node 2" : "%24"

			},
			{
				"node 1" : "%40",
				"node 2" : "%25"

			},
			{
				"node 1" : "%40",
				"node 2" : "%46"

			},
			{
				"node 1" : "%40",
				"node 2" : "%26"

			},
			{
				"node 1" : "%40",
				"node 2" : "%27"

			},
			{
				"node 1" : "%40",
				"node 2" : "%28"

			},
			{
				"node 1" : "%40",
				"node 2" : "%29"

			},
			{
				"node 1" : "%40",
				"node 2" : "%30"

			},
			{
				"node 1" : "%40",
				"node 2" : "%31"

			},
			{
				"node 1" : "%40",
				"node 2" : "%32"

			},
			{
				"node 1" : "%40",
				"node 2" : "%33"

			},
			{
				"node 1" : "%40",
				"node 2" : "%34"

			},
			{
				"node 1" : "%40",
				"node 2" : "%35"

			},
			{
				"node 1" : "%40",
				"node 2" : "%36"

			},
			{
				"node 1" : "%40",
				"node 2" : "%37"

			},
			{
				"node 1" : "%40",
				"node 2" : "%38"

			},
			{
				"node 1" : "%40",
				"node 2" : "%39"

			},
			{
				"node 1" : "%.03",
				"node 2" : "%41"

			},
			{
				"node 1" : "%.03",
				"node 2" : "%22"

			},
			{
				"node 1" : "%.03",
				"node 2" : "%23"

			},
			{
				"node 1" : "%.03",
				"node 2" : "%24"

			},
			{
				"node 1" : "%.03",
				"node 2" : "%25"

			},
			{
				"node 1" : "%.03",
				"node 2" : "%46"

			},
			{
				"node 1" : "%.03",
				"node 2" : "%26"

			},
			{
				"node 1" : "%.03",
				"node 2" : "%27"

			},
			{
				"node 1" : "%.03",
				"node 2" : "%28"

			},
			{
				"node 1" : "%.03",
				"node 2" : "%29"

			},
			{
				"node 1" : "%.03",
				"node 2" : "%30"

			},
			{
				"node 1" : "%.03",
				"node 2" : "%31"

			},
			{
				"node 1" : "%.03",
				"node 2" : "%32"

			},
			{
				"node 1" : "%.03",
				"node 2" : "%33"

			},
			{
				"node 1" : "%.03",
				"node 2" : "%34"

			},
			{
				"node 1" : "%.03",
				"node 2" : "%35"

			},
			{
				"node 1" : "%.03",
				"node 2" : "%36"

			},
			{
				"node 1" : "%.03",
				"node 2" : "%37"

			},
			{
				"node 1" : "%.03",
				"node 2" : "%38"

			},
			{
				"node 1" : "%.03",
				"node 2" : "%39"

			},
			{
				"node 1" : "%41",
				"node 2" : "%22"

			},
			{
				"node 1" : "%41",
				"node 2" : "%23"

			},
			{
				"node 1" : "%41",
				"node 2" : "%24"

			},
			{
				"node 1" : "%41",
				"node 2" : "%25"

			},
			{
				"node 1" : "%41",
				"node 2" : "%46"

			},
			{
				"node 1" : "%41",
				"node 2" : "%26"

			},
			{
				"node 1" : "%41",
				"node 2" : "%27"

			},
			{
				"node 1" : "%41",
				"node 2" : "%28"

			},
			{
				"node 1" : "%41",
				"node 2" : "%29"

			},
			{
				"node 1" : "%41",
				"node 2" : "%30"

			},
			{
				"node 1" : "%41",
				"node 2" : "%31"

			},
			{
				"node 1" : "%41",
				"node 2" : "%32"

			},
			{
				"node 1" : "%41",
				"node 2" : "%33"

			},
			{
				"node 1" : "%41",
				"node 2" : "%34"

			},
			{
				"node 1" : "%41",
				"node 2" : "%35"

			},
			{
				"node 1" : "%41",
				"node 2" : "%36"

			},
			{
				"node 1" : "%41",
				"node 2" : "%37"

			},
			{
				"node 1" : "%41",
				"node 2" : "%38"

			},
			{
				"node 1" : "%41",
				"node 2" : "%39"

			},
			{
				"node 1" : "%22",
				"node 2" : "%23"

			},
			{
				"node 1" : "%23",
				"node 2" : "%24"

			},
			{
				"node 1" : "%24",
				"node 2" : "%25"

			},
			{
				"node 1" : "%24",
				"node 2" : "%46"

			},
			{
				"node 1" : "%25",
				"node 2" : "%46"

			},
			{
				"node 1" : "%25",
				"node 2" : "%26"

			},
			{
				"node 1" : "%25",
				"node 2" : "%27"

			},
			{
				"node 1" : "%25",
				"node 2" : "%28"

			},
			{
				"node 1" : "%25",
				"node 2" : "%29"

			},
			{
				"node 1" : "%25",
				"node 2" : "%30"

			},
			{
				"node 1" : "%25",
				"node 2" : "%31"

			},
			{
				"node 1" : "%25",
				"node 2" : "%32"

			},
			{
				"node 1" : "%25",
				"node 2" : "%33"

			},
			{
				"node 1" : "%25",
				"node 2" : "%34"

			},
			{
				"node 1" : "%25",
				"node 2" : "%35"

			},
			{
				"node 1" : "%25",
				"node 2" : "%36"

			},
			{
				"node 1" : "%25",
				"node 2" : "%37"

			},
			{
				"node 1" : "%25",
				"node 2" : "%38"

			},
			{
				"node 1" : "%25",
				"node 2" : "%39"

			},
			{
				"node 1" : "%46",
				"node 2" : "%26"

			},
			{
				"node 1" : "%46",
				"node 2" : "%27"

			},
			{
				"node 1" : "%46",
				"node 2" : "%28"

			},
			{
				"node 1" : "%46",
				"node 2" : "%29"

			},
			{
				"node 1" : "%46",
				"node 2" : "%30"

			},
			{
				"node 1" : "%46",
				"node 2" : "%31"

			},
			{
				"node 1" : "%46",
				"node 2" : "%32"

			},
			{
				"node 1" : "%46",
				"node 2" : "%33"

			},
			{
				"node 1" : "%46",
				"node 2" : "%34"

			},
			{
				"node 1" : "%46",
				"node 2" : "%35"

			},
			{
				"node 1" : "%46",
				"node 2" : "%36"

			},
			{
				"node 1" : "%46",
				"node 2" : "%37"

			},
			{
				"node 1" : "%46",
				"node 2" : "%38"

			},
			{
				"node 1" : "%46",
				"node 2" : "%39"

			},
			{
				"node 1" : "%46",
				"node 2" : "%43"

			},
			{
				"node 1" : "%46",
				"node 2" : "%44"

			},
			{
				"node 1" : "%46",
				"node 2" : "%45"

			},
			{
				"node 1" : "%46",
				"node 2" : "%94"

			},
			{
				"node 1" : "%46",
				"node 2" : "%47"

			},
			{
				"node 1" : "%46",
				"node 2" : "%48"

			},
			{
				"node 1" : "%46",
				"node 2" : "%49"

			},
			{
				"node 1" : "%46",
				"node 2" : "%50"

			},
			{
				"node 1" : "%46",
				"node 2" : "%51"

			},
			{
				"node 1" : "%46",
				"node 2" : "%52"

			},
			{
				"node 1" : "%46",
				"node 2" : "%53"

			},
			{
				"node 1" : "%46",
				"node 2" : "%54"

			},
			{
				"node 1" : "%46",
				"node 2" : "%55"

			},
			{
				"node 1" : "%46",
				"node 2" : "%70"

			},
			{
				"node 1" : "%46",
				"node 2" : "%56"

			},
			{
				"node 1" : "%46",
				"node 2" : "%81"

			},
			{
				"node 1" : "%46",
				"node 2" : "%.05"

			},
			{
				"node 1" : "%46",
				"node 2" : "%82"

			},
			{
				"node 1" : "%46",
				"node 2" : "%.04"

			},
			{
				"node 1" : "%46",
				"node 2" : "%.1"

			},
			{
				"node 1" : "%46",
				"node 2" : "%57"

			},
			{
				"node 1" : "%46",
				"node 2" : "%58"

			},
			{
				"node 1" : "%46",
				"node 2" : "%59"

			},
			{
				"node 1" : "%46",
				"node 2" : "%83"

			},
			{
				"node 1" : "%46",
				"node 2" : "%60"

			},
			{
				"node 1" : "%46",
				"node 2" : "%61"

			},
			{
				"node 1" : "%46",
				"node 2" : "%62"

			},
			{
				"node 1" : "%46",
				"node 2" : "%63"

			},
			{
				"node 1" : "%46",
				"node 2" : "%64"

			},
			{
				"node 1" : "%46",
				"node 2" : "%65"

			},
			{
				"node 1" : "%46",
				"node 2" : "%66"

			},
			{
				"node 1" : "%46",
				"node 2" : "%67"

			},
			{
				"node 1" : "%46",
				"node 2" : "%68"

			},
			{
				"node 1" : "%46",
				"node 2" : "%74"

			},
			{
				"node 1" : "%46",
				"node 2" : "%69"

			},
			{
				"node 1" : "%46",
				"node 2" : "%80"

			},
			{
				"node 1" : "%46",
				"node 2" : "%91"

			},
			{
				"node 1" : "%26",
				"node 2" : "%27"

			},
			{
				"node 1" : "%27",
				"node 2" : "%28"

			},
			{
				"node 1" : "%28",
				"node 2" : "%29"

			},
			{
				"node 1" : "%29",
				"node 2" : "%30"

			},
			{
				"node 1" : "%29",
				"node 2" : "%31"

			},
			{
				"node 1" : "%29",
				"node 2" : "%32"

			},
			{
				"node 1" : "%29",
				"node 2" : "%33"

			},
			{
				"node 1" : "%29",
				"node 2" : "%34"

			},
			{
				"node 1" : "%29",
				"node 2" : "%35"

			},
			{
				"node 1" : "%30",
				"node 2" : "%31"

			},
			{
				"node 1" : "%31",
				"node 2" : "%32"

			},
			{
				"node 1" : "%32",
				"node 2" : "%33"

			},
			{
				"node 1" : "%33",
				"node 2" : "%34"

			},
			{
				"node 1" : "%34",
				"node 2" : "%35"

			},
			{
				"node 1" : "%35",
				"node 2" : "%36"

			},
			{
				"node 1" : "%35",
				"node 2" : "%37"

			},
			{
				"node 1" : "%35",
				"node 2" : "%38"

			},
			{
				"node 1" : "%35",
				"node 2" : "%39"

			},
			{
				"node 1" : "%36",
				"node 2" : "%37"

			},
			{
				"node 1" : "%37",
				"node 2" : "%38"

			},
			{
				"node 1" : "%37",
				"node 2" : "%39"

			},
			{
				"node 1" : "%38",
				"node 2" : "%39"

			},
			{
				"node 1" : "%43",
				"node 2" : "%44"

			},
			{
				"node 1" : "%43",
				"node 2" : "%45"

			},
			{
				"node 1" : "%44",
				"node 2" : "%45"

			},
			{
				"node 1" : "%44",
				"node 2" : "%94"

			},
			{
				"node 1" : "%44",
				"node 2" : "%47"

			},
			{
				"node 1" : "%44",
				"node 2" : "%48"

			},
			{
				"node 1" : "%44",
				"node 2" : "%49"

			},
			{
				"node 1" : "%44",
				"node 2" : "%50"

			},
			{
				"node 1" : "%44",
				"node 2" : "%51"

			},
			{
				"node 1" : "%44",
				"node 2" : "%52"

			},
			{
				"node 1" : "%44",
				"node 2" : "%53"

			},
			{
				"node 1" : "%44",
				"node 2" : "%54"

			},
			{
				"node 1" : "%44",
				"node 2" : "%55"

			},
			{
				"node 1" : "%44",
				"node 2" : "%70"

			},
			{
				"node 1" : "%44",
				"node 2" : "%56"

			},
			{
				"node 1" : "%44",
				"node 2" : "%81"

			},
			{
				"node 1" : "%44",
				"node 2" : "%.05"

			},
			{
				"node 1" : "%44",
				"node 2" : "%82"

			},
			{
				"node 1" : "%44",
				"node 2" : "%.04"

			},
			{
				"node 1" : "%44",
				"node 2" : "%.1"

			},
			{
				"node 1" : "%44",
				"node 2" : "%57"

			},
			{
				"node 1" : "%44",
				"node 2" : "%58"

			},
			{
				"node 1" : "%44",
				"node 2" : "%59"

			},
			{
				"node 1" : "%44",
				"node 2" : "%83"

			},
			{
				"node 1" : "%44",
				"node 2" : "%60"

			},
			{
				"node 1" : "%44",
				"node 2" : "%61"

			},
			{
				"node 1" : "%44",
				"node 2" : "%62"

			},
			{
				"node 1" : "%44",
				"node 2" : "%63"

			},
			{
				"node 1" : "%44",
				"node 2" : "%64"

			},
			{
				"node 1" : "%44",
				"node 2" : "%65"

			},
			{
				"node 1" : "%44",
				"node 2" : "%66"

			},
			{
				"node 1" : "%44",
				"node 2" : "%67"

			},
			{
				"node 1" : "%44",
				"node 2" : "%68"

			},
			{
				"node 1" : "%44",
				"node 2" : "%74"

			},
			{
				"node 1" : "%44",
				"node 2" : "%69"

			},
			{
				"node 1" : "%44",
				"node 2" : "%80"

			},
			{
				"node 1" : "%44",
				"node 2" : "%91"

			},
			{
				"node 1" : "%44",
				"node 2" : "%71"

			},
			{
				"node 1" : "%44",
				"node 2" : "%72"

			},
			{
				"node 1" : "%44",
				"node 2" : "%73"

			},
			{
				"node 1" : "%44",
				"node 2" : "%75"

			},
			{
				"node 1" : "%44",
				"node 2" : "%76"

			},
			{
				"node 1" : "%44",
				"node 2" : "%77"

			},
			{
				"node 1" : "%44",
				"node 2" : "%78"

			},
			{
				"node 1" : "%44",
				"node 2" : "%79"

			},
			{
				"node 1" : "%44",
				"node 2" : "%84"

			},
			{
				"node 1" : "%44",
				"node 2" : "%85"

			},
			{
				"node 1" : "%44",
				"node 2" : "%86"

			},
			{
				"node 1" : "%44",
				"node 2" : "%87"

			},
			{
				"node 1" : "%44",
				"node 2" : "%88"

			},
			{
				"node 1" : "%44",
				"node 2" : "%89"

			},
			{
				"node 1" : "%44",
				"node 2" : "%90"

			},
			{
				"node 1" : "%44",
				"node 2" : "%92"

			},
			{
				"node 1" : "%44",
				"node 2" : "%93"

			},
			{
				"node 1" : "%44",
				"node 2" : "%.02"

			},
			{
				"node 1" : "%44",
				"node 2" : "%.01"

			},
			{
				"node 1" : "%45",
				"node 2" : "%94"

			},
			{
				"node 1" : "%45",
				"node 2" : "%47"

			},
			{
				"node 1" : "%45",
				"node 2" : "%48"

			},
			{
				"node 1" : "%45",
				"node 2" : "%49"

			},
			{
				"node 1" : "%45",
				"node 2" : "%50"

			},
			{
				"node 1" : "%45",
				"node 2" : "%51"

			},
			{
				"node 1" : "%45",
				"node 2" : "%52"

			},
			{
				"node 1" : "%45",
				"node 2" : "%53"

			},
			{
				"node 1" : "%45",
				"node 2" : "%54"

			},
			{
				"node 1" : "%45",
				"node 2" : "%55"

			},
			{
				"node 1" : "%45",
				"node 2" : "%70"

			},
			{
				"node 1" : "%45",
				"node 2" : "%56"

			},
			{
				"node 1" : "%45",
				"node 2" : "%81"

			},
			{
				"node 1" : "%45",
				"node 2" : "%.05"

			},
			{
				"node 1" : "%45",
				"node 2" : "%82"

			},
			{
				"node 1" : "%45",
				"node 2" : "%.04"

			},
			{
				"node 1" : "%45",
				"node 2" : "%.1"

			},
			{
				"node 1" : "%45",
				"node 2" : "%57"

			},
			{
				"node 1" : "%45",
				"node 2" : "%58"

			},
			{
				"node 1" : "%45",
				"node 2" : "%59"

			},
			{
				"node 1" : "%45",
				"node 2" : "%83"

			},
			{
				"node 1" : "%45",
				"node 2" : "%60"

			},
			{
				"node 1" : "%45",
				"node 2" : "%61"

			},
			{
				"node 1" : "%45",
				"node 2" : "%62"

			},
			{
				"node 1" : "%45",
				"node 2" : "%63"

			},
			{
				"node 1" : "%45",
				"node 2" : "%64"

			},
			{
				"node 1" : "%45",
				"node 2" : "%65"

			},
			{
				"node 1" : "%45",
				"node 2" : "%66"

			},
			{
				"node 1" : "%45",
				"node 2" : "%67"

			},
			{
				"node 1" : "%45",
				"node 2" : "%68"

			},
			{
				"node 1" : "%45",
				"node 2" : "%74"

			},
			{
				"node 1" : "%45",
				"node 2" : "%69"

			},
			{
				"node 1" : "%45",
				"node 2" : "%80"

			},
			{
				"node 1" : "%45",
				"node 2" : "%91"

			},
			{
				"node 1" : "%45",
				"node 2" : "%71"

			},
			{
				"node 1" : "%45",
				"node 2" : "%72"

			},
			{
				"node 1" : "%45",
				"node 2" : "%73"

			},
			{
				"node 1" : "%45",
				"node 2" : "%75"

			},
			{
				"node 1" : "%45",
				"node 2" : "%76"

			},
			{
				"node 1" : "%45",
				"node 2" : "%77"

			},
			{
				"node 1" : "%45",
				"node 2" : "%78"

			},
			{
				"node 1" : "%45",
				"node 2" : "%79"

			},
			{
				"node 1" : "%45",
				"node 2" : "%84"

			},
			{
				"node 1" : "%45",
				"node 2" : "%85"

			},
			{
				"node 1" : "%45",
				"node 2" : "%86"

			},
			{
				"node 1" : "%45",
				"node 2" : "%87"

			},
			{
				"node 1" : "%45",
				"node 2" : "%88"

			},
			{
				"node 1" : "%45",
				"node 2" : "%89"

			},
			{
				"node 1" : "%45",
				"node 2" : "%90"

			},
			{
				"node 1" : "%45",
				"node 2" : "%92"

			},
			{
				"node 1" : "%45",
				"node 2" : "%93"

			},
			{
				"node 1" : "%45",
				"node 2" : "%.02"

			},
			{
				"node 1" : "%94",
				"node 2" : "%47"

			},
			{
				"node 1" : "%94",
				"node 2" : "%48"

			},
			{
				"node 1" : "%94",
				"node 2" : "%49"

			},
			{
				"node 1" : "%94",
				"node 2" : "%50"

			},
			{
				"node 1" : "%94",
				"node 2" : "%51"

			},
			{
				"node 1" : "%94",
				"node 2" : "%52"

			},
			{
				"node 1" : "%94",
				"node 2" : "%53"

			},
			{
				"node 1" : "%94",
				"node 2" : "%54"

			},
			{
				"node 1" : "%94",
				"node 2" : "%55"

			},
			{
				"node 1" : "%94",
				"node 2" : "%70"

			},
			{
				"node 1" : "%94",
				"node 2" : "%56"

			},
			{
				"node 1" : "%94",
				"node 2" : "%81"

			},
			{
				"node 1" : "%94",
				"node 2" : "%.05"

			},
			{
				"node 1" : "%94",
				"node 2" : "%82"

			},
			{
				"node 1" : "%94",
				"node 2" : "%.04"

			},
			{
				"node 1" : "%94",
				"node 2" : "%.1"

			},
			{
				"node 1" : "%94",
				"node 2" : "%57"

			},
			{
				"node 1" : "%94",
				"node 2" : "%58"

			},
			{
				"node 1" : "%94",
				"node 2" : "%59"

			},
			{
				"node 1" : "%94",
				"node 2" : "%83"

			},
			{
				"node 1" : "%94",
				"node 2" : "%60"

			},
			{
				"node 1" : "%94",
				"node 2" : "%61"

			},
			{
				"node 1" : "%94",
				"node 2" : "%62"

			},
			{
				"node 1" : "%94",
				"node 2" : "%63"

			},
			{
				"node 1" : "%94",
				"node 2" : "%64"

			},
			{
				"node 1" : "%94",
				"node 2" : "%65"

			},
			{
				"node 1" : "%94",
				"node 2" : "%66"

			},
			{
				"node 1" : "%94",
				"node 2" : "%67"

			},
			{
				"node 1" : "%94",
				"node 2" : "%68"

			},
			{
				"node 1" : "%94",
				"node 2" : "%74"

			},
			{
				"node 1" : "%94",
				"node 2" : "%69"

			},
			{
				"node 1" : "%94",
				"node 2" : "%80"

			},
			{
				"node 1" : "%94",
				"node 2" : "%91"

			},
			{
				"node 1" : "%94",
				"node 2" : "%71"

			},
			{
				"node 1" : "%94",
				"node 2" : "%72"

			},
			{
				"node 1" : "%94",
				"node 2" : "%73"

			},
			{
				"node 1" : "%47",
				"node 2" : "%48"

			},
			{
				"node 1" : "%49",
				"node 2" : "%50"

			},
			{
				"node 1" : "%51",
				"node 2" : "%52"

			},
			{
				"node 1" : "%52",
				"node 2" : "%53"

			},
			{
				"node 1" : "%52",
				"node 2" : "%54"

			},
			{
				"node 1" : "%53",
				"node 2" : "%54"

			},
			{
				"node 1" : "%55",
				"node 2" : "%70"

			},
			{
				"node 1" : "%55",
				"node 2" : "%56"

			},
			{
				"node 1" : "%55",
				"node 2" : "%81"

			},
			{
				"node 1" : "%55",
				"node 2" : "%.05"

			},
			{
				"node 1" : "%55",
				"node 2" : "%82"

			},
			{
				"node 1" : "%55",
				"node 2" : "%.04"

			},
			{
				"node 1" : "%55",
				"node 2" : "%.1"

			},
			{
				"node 1" : "%70",
				"node 2" : "%56"

			},
			{
				"node 1" : "%70",
				"node 2" : "%81"

			},
			{
				"node 1" : "%70",
				"node 2" : "%.05"

			},
			{
				"node 1" : "%70",
				"node 2" : "%82"

			},
			{
				"node 1" : "%70",
				"node 2" : "%.04"

			},
			{
				"node 1" : "%70",
				"node 2" : "%.1"

			},
			{
				"node 1" : "%70",
				"node 2" : "%57"

			},
			{
				"node 1" : "%70",
				"node 2" : "%58"

			},
			{
				"node 1" : "%70",
				"node 2" : "%59"

			},
			{
				"node 1" : "%70",
				"node 2" : "%83"

			},
			{
				"node 1" : "%70",
				"node 2" : "%60"

			},
			{
				"node 1" : "%70",
				"node 2" : "%61"

			},
			{
				"node 1" : "%70",
				"node 2" : "%62"

			},
			{
				"node 1" : "%70",
				"node 2" : "%63"

			},
			{
				"node 1" : "%70",
				"node 2" : "%64"

			},
			{
				"node 1" : "%70",
				"node 2" : "%65"

			},
			{
				"node 1" : "%70",
				"node 2" : "%66"

			},
			{
				"node 1" : "%70",
				"node 2" : "%67"

			},
			{
				"node 1" : "%70",
				"node 2" : "%68"

			},
			{
				"node 1" : "%70",
				"node 2" : "%74"

			},
			{
				"node 1" : "%70",
				"node 2" : "%69"

			},
			{
				"node 1" : "%70",
				"node 2" : "%80"

			},
			{
				"node 1" : "%70",
				"node 2" : "%91"

			},
			{
				"node 1" : "%70",
				"node 2" : "%71"

			},
			{
				"node 1" : "%70",
				"node 2" : "%72"

			},
			{
				"node 1" : "%70",
				"node 2" : "%73"

			},
			{
				"node 1" : "%70",
				"node 2" : "%75"

			},
			{
				"node 1" : "%70",
				"node 2" : "%76"

			},
			{
				"node 1" : "%70",
				"node 2" : "%77"

			},
			{
				"node 1" : "%70",
				"node 2" : "%78"

			},
			{
				"node 1" : "%70",
				"node 2" : "%79"

			},
			{
				"node 1" : "%70",
				"node 2" : "%84"

			},
			{
				"node 1" : "%70",
				"node 2" : "%85"

			},
			{
				"node 1" : "%70",
				"node 2" : "%86"

			},
			{
				"node 1" : "%70",
				"node 2" : "%87"

			},
			{
				"node 1" : "%70",
				"node 2" : "%88"

			},
			{
				"node 1" : "%70",
				"node 2" : "%89"

			},
			{
				"node 1" : "%70",
				"node 2" : "%90"

			},
			{
				"node 1" : "%70",
				"node 2" : "%92"

			},
			{
				"node 1" : "%70",
				"node 2" : "%93"

			},
			{
				"node 1" : "%70",
				"node 2" : "%.02"

			},
			{
				"node 1" : "%70",
				"node 2" : "%.01"

			},
			{
				"node 1" : "%56",
				"node 2" : "%81"

			},
			{
				"node 1" : "%56",
				"node 2" : "%.05"

			},
			{
				"node 1" : "%56",
				"node 2" : "%82"

			},
			{
				"node 1" : "%56",
				"node 2" : "%.04"

			},
			{
				"node 1" : "%56",
				"node 2" : "%.1"

			},
			{
				"node 1" : "%56",
				"node 2" : "%57"

			},
			{
				"node 1" : "%56",
				"node 2" : "%58"

			},
			{
				"node 1" : "%56",
				"node 2" : "%59"

			},
			{
				"node 1" : "%56",
				"node 2" : "%83"

			},
			{
				"node 1" : "%56",
				"node 2" : "%60"

			},
			{
				"node 1" : "%56",
				"node 2" : "%61"

			},
			{
				"node 1" : "%56",
				"node 2" : "%62"

			},
			{
				"node 1" : "%56",
				"node 2" : "%63"

			},
			{
				"node 1" : "%56",
				"node 2" : "%64"

			},
			{
				"node 1" : "%56",
				"node 2" : "%65"

			},
			{
				"node 1" : "%56",
				"node 2" : "%66"

			},
			{
				"node 1" : "%56",
				"node 2" : "%67"

			},
			{
				"node 1" : "%56",
				"node 2" : "%68"

			},
			{
				"node 1" : "%56",
				"node 2" : "%74"

			},
			{
				"node 1" : "%56",
				"node 2" : "%69"

			},
			{
				"node 1" : "%56",
				"node 2" : "%80"

			},
			{
				"node 1" : "%56",
				"node 2" : "%91"

			},
			{
				"node 1" : "%56",
				"node 2" : "%71"

			},
			{
				"node 1" : "%56",
				"node 2" : "%72"

			},
			{
				"node 1" : "%56",
				"node 2" : "%73"

			},
			{
				"node 1" : "%56",
				"node 2" : "%75"

			},
			{
				"node 1" : "%56",
				"node 2" : "%76"

			},
			{
				"node 1" : "%56",
				"node 2" : "%77"

			},
			{
				"node 1" : "%56",
				"node 2" : "%78"

			},
			{
				"node 1" : "%56",
				"node 2" : "%79"

			},
			{
				"node 1" : "%81",
				"node 2" : "%.05"

			},
			{
				"node 1" : "%81",
				"node 2" : "%82"

			},
			{
				"node 1" : "%81",
				"node 2" : "%.04"

			},
			{
				"node 1" : "%81",
				"node 2" : "%.1"

			},
			{
				"node 1" : "%81",
				"node 2" : "%57"

			},
			{
				"node 1" : "%81",
				"node 2" : "%58"

			},
			{
				"node 1" : "%81",
				"node 2" : "%59"

			},
			{
				"node 1" : "%81",
				"node 2" : "%83"

			},
			{
				"node 1" : "%81",
				"node 2" : "%60"

			},
			{
				"node 1" : "%81",
				"node 2" : "%61"

			},
			{
				"node 1" : "%81",
				"node 2" : "%62"

			},
			{
				"node 1" : "%81",
				"node 2" : "%63"

			},
			{
				"node 1" : "%81",
				"node 2" : "%64"

			},
			{
				"node 1" : "%81",
				"node 2" : "%65"

			},
			{
				"node 1" : "%81",
				"node 2" : "%66"

			},
			{
				"node 1" : "%81",
				"node 2" : "%67"

			},
			{
				"node 1" : "%81",
				"node 2" : "%68"

			},
			{
				"node 1" : "%81",
				"node 2" : "%74"

			},
			{
				"node 1" : "%81",
				"node 2" : "%69"

			},
			{
				"node 1" : "%81",
				"node 2" : "%80"

			},
			{
				"node 1" : "%81",
				"node 2" : "%91"

			},
			{
				"node 1" : "%81",
				"node 2" : "%71"

			},
			{
				"node 1" : "%81",
				"node 2" : "%72"

			},
			{
				"node 1" : "%81",
				"node 2" : "%73"

			},
			{
				"node 1" : "%81",
				"node 2" : "%75"

			},
			{
				"node 1" : "%81",
				"node 2" : "%76"

			},
			{
				"node 1" : "%81",
				"node 2" : "%77"

			},
			{
				"node 1" : "%81",
				"node 2" : "%78"

			},
			{
				"node 1" : "%81",
				"node 2" : "%79"

			},
			{
				"node 1" : "%.05",
				"node 2" : "%82"

			},
			{
				"node 1" : "%.05",
				"node 2" : "%.04"

			},
			{
				"node 1" : "%.05",
				"node 2" : "%.1"

			},
			{
				"node 1" : "%.05",
				"node 2" : "%57"

			},
			{
				"node 1" : "%.05",
				"node 2" : "%58"

			},
			{
				"node 1" : "%.05",
				"node 2" : "%59"

			},
			{
				"node 1" : "%.05",
				"node 2" : "%83"

			},
			{
				"node 1" : "%.05",
				"node 2" : "%60"

			},
			{
				"node 1" : "%.05",
				"node 2" : "%61"

			},
			{
				"node 1" : "%.05",
				"node 2" : "%62"

			},
			{
				"node 1" : "%.05",
				"node 2" : "%63"

			},
			{
				"node 1" : "%.05",
				"node 2" : "%64"

			},
			{
				"node 1" : "%.05",
				"node 2" : "%65"

			},
			{
				"node 1" : "%.05",
				"node 2" : "%66"

			},
			{
				"node 1" : "%.05",
				"node 2" : "%67"

			},
			{
				"node 1" : "%.05",
				"node 2" : "%68"

			},
			{
				"node 1" : "%.05",
				"node 2" : "%74"

			},
			{
				"node 1" : "%.05",
				"node 2" : "%69"

			},
			{
				"node 1" : "%.05",
				"node 2" : "%80"

			},
			{
				"node 1" : "%.05",
				"node 2" : "%91"

			},
			{
				"node 1" : "%.05",
				"node 2" : "%71"

			},
			{
				"node 1" : "%.05",
				"node 2" : "%72"

			},
			{
				"node 1" : "%.05",
				"node 2" : "%73"

			},
			{
				"node 1" : "%.05",
				"node 2" : "%75"

			},
			{
				"node 1" : "%.05",
				"node 2" : "%76"

			},
			{
				"node 1" : "%.05",
				"node 2" : "%77"

			},
			{
				"node 1" : "%.05",
				"node 2" : "%78"

			},
			{
				"node 1" : "%.05",
				"node 2" : "%79"

			},
			{
				"node 1" : "%82",
				"node 2" : "%.04"

			},
			{
				"node 1" : "%82",
				"node 2" : "%.1"

			},
			{
				"node 1" : "%82",
				"node 2" : "%57"

			},
			{
				"node 1" : "%82",
				"node 2" : "%58"

			},
			{
				"node 1" : "%82",
				"node 2" : "%59"

			},
			{
				"node 1" : "%82",
				"node 2" : "%83"

			},
			{
				"node 1" : "%82",
				"node 2" : "%60"

			},
			{
				"node 1" : "%82",
				"node 2" : "%61"

			},
			{
				"node 1" : "%82",
				"node 2" : "%62"

			},
			{
				"node 1" : "%82",
				"node 2" : "%63"

			},
			{
				"node 1" : "%82",
				"node 2" : "%64"

			},
			{
				"node 1" : "%82",
				"node 2" : "%65"

			},
			{
				"node 1" : "%82",
				"node 2" : "%66"

			},
			{
				"node 1" : "%82",
				"node 2" : "%67"

			},
			{
				"node 1" : "%82",
				"node 2" : "%68"

			},
			{
				"node 1" : "%82",
				"node 2" : "%74"

			},
			{
				"node 1" : "%82",
				"node 2" : "%69"

			},
			{
				"node 1" : "%82",
				"node 2" : "%80"

			},
			{
				"node 1" : "%82",
				"node 2" : "%91"

			},
			{
				"node 1" : "%82",
				"node 2" : "%71"

			},
			{
				"node 1" : "%82",
				"node 2" : "%72"

			},
			{
				"node 1" : "%82",
				"node 2" : "%73"

			},
			{
				"node 1" : "%82",
				"node 2" : "%75"

			},
			{
				"node 1" : "%82",
				"node 2" : "%76"

			},
			{
				"node 1" : "%82",
				"node 2" : "%77"

			},
			{
				"node 1" : "%82",
				"node 2" : "%78"

			},
			{
				"node 1" : "%82",
				"node 2" : "%79"

			},
			{
				"node 1" : "%.04",
				"node 2" : "%.1"

			},
			{
				"node 1" : "%.04",
				"node 2" : "%57"

			},
			{
				"node 1" : "%.04",
				"node 2" : "%58"

			},
			{
				"node 1" : "%.04",
				"node 2" : "%59"

			},
			{
				"node 1" : "%.04",
				"node 2" : "%83"

			},
			{
				"node 1" : "%.04",
				"node 2" : "%60"

			},
			{
				"node 1" : "%.04",
				"node 2" : "%61"

			},
			{
				"node 1" : "%.04",
				"node 2" : "%62"

			},
			{
				"node 1" : "%.04",
				"node 2" : "%63"

			},
			{
				"node 1" : "%.04",
				"node 2" : "%64"

			},
			{
				"node 1" : "%.04",
				"node 2" : "%65"

			},
			{
				"node 1" : "%.04",
				"node 2" : "%66"

			},
			{
				"node 1" : "%.04",
				"node 2" : "%67"

			},
			{
				"node 1" : "%.04",
				"node 2" : "%68"

			},
			{
				"node 1" : "%.04",
				"node 2" : "%74"

			},
			{
				"node 1" : "%.04",
				"node 2" : "%69"

			},
			{
				"node 1" : "%.04",
				"node 2" : "%80"

			},
			{
				"node 1" : "%.04",
				"node 2" : "%91"

			},
			{
				"node 1" : "%.04",
				"node 2" : "%71"

			},
			{
				"node 1" : "%.04",
				"node 2" : "%72"

			},
			{
				"node 1" : "%.04",
				"node 2" : "%73"

			},
			{
				"node 1" : "%.04",
				"node 2" : "%75"

			},
			{
				"node 1" : "%.04",
				"node 2" : "%76"

			},
			{
				"node 1" : "%.04",
				"node 2" : "%77"

			},
			{
				"node 1" : "%.04",
				"node 2" : "%78"

			},
			{
				"node 1" : "%.04",
				"node 2" : "%79"

			},
			{
				"node 1" : "%.04",
				"node 2" : "%84"

			},
			{
				"node 1" : "%.04",
				"node 2" : "%85"

			},
			{
				"node 1" : "%.1",
				"node 2" : "%57"

			},
			{
				"node 1" : "%.1",
				"node 2" : "%58"

			},
			{
				"node 1" : "%.1",
				"node 2" : "%59"

			},
			{
				"node 1" : "%.1",
				"node 2" : "%83"

			},
			{
				"node 1" : "%.1",
				"node 2" : "%60"

			},
			{
				"node 1" : "%.1",
				"node 2" : "%61"

			},
			{
				"node 1" : "%.1",
				"node 2" : "%62"

			},
			{
				"node 1" : "%.1",
				"node 2" : "%63"

			},
			{
				"node 1" : "%.1",
				"node 2" : "%64"

			},
			{
				"node 1" : "%.1",
				"node 2" : "%65"

			},
			{
				"node 1" : "%.1",
				"node 2" : "%66"

			},
			{
				"node 1" : "%.1",
				"node 2" : "%67"

			},
			{
				"node 1" : "%.1",
				"node 2" : "%68"

			},
			{
				"node 1" : "%.1",
				"node 2" : "%74"

			},
			{
				"node 1" : "%.1",
				"node 2" : "%69"

			},
			{
				"node 1" : "%.1",
				"node 2" : "%80"

			},
			{
				"node 1" : "%.1",
				"node 2" : "%91"

			},
			{
				"node 1" : "%.1",
				"node 2" : "%71"

			},
			{
				"node 1" : "%.1",
				"node 2" : "%72"

			},
			{
				"node 1" : "%.1",
				"node 2" : "%73"

			},
			{
				"node 1" : "%.1",
				"node 2" : "%75"

			},
			{
				"node 1" : "%.1",
				"node 2" : "%76"

			},
			{
				"node 1" : "%.1",
				"node 2" : "%77"

			},
			{
				"node 1" : "%.1",
				"node 2" : "%78"

			},
			{
				"node 1" : "%.1",
				"node 2" : "%79"

			},
			{
				"node 1" : "%57",
				"node 2" : "%58"

			},
			{
				"node 1" : "%58",
				"node 2" : "%59"

			},
			{
				"node 1" : "%58",
				"node 2" : "%83"

			},
			{
				"node 1" : "%59",
				"node 2" : "%83"

			},
			{
				"node 1" : "%59",
				"node 2" : "%60"

			},
			{
				"node 1" : "%59",
				"node 2" : "%61"

			},
			{
				"node 1" : "%59",
				"node 2" : "%62"

			},
			{
				"node 1" : "%59",
				"node 2" : "%63"

			},
			{
				"node 1" : "%59",
				"node 2" : "%64"

			},
			{
				"node 1" : "%59",
				"node 2" : "%65"

			},
			{
				"node 1" : "%59",
				"node 2" : "%66"

			},
			{
				"node 1" : "%59",
				"node 2" : "%67"

			},
			{
				"node 1" : "%59",
				"node 2" : "%68"

			},
			{
				"node 1" : "%59",
				"node 2" : "%74"

			},
			{
				"node 1" : "%59",
				"node 2" : "%69"

			},
			{
				"node 1" : "%59",
				"node 2" : "%80"

			},
			{
				"node 1" : "%59",
				"node 2" : "%91"

			},
			{
				"node 1" : "%59",
				"node 2" : "%71"

			},
			{
				"node 1" : "%59",
				"node 2" : "%72"

			},
			{
				"node 1" : "%59",
				"node 2" : "%73"

			},
			{
				"node 1" : "%83",
				"node 2" : "%60"

			},
			{
				"node 1" : "%83",
				"node 2" : "%61"

			},
			{
				"node 1" : "%83",
				"node 2" : "%62"

			},
			{
				"node 1" : "%83",
				"node 2" : "%63"

			},
			{
				"node 1" : "%83",
				"node 2" : "%64"

			},
			{
				"node 1" : "%83",
				"node 2" : "%65"

			},
			{
				"node 1" : "%83",
				"node 2" : "%66"

			},
			{
				"node 1" : "%83",
				"node 2" : "%67"

			},
			{
				"node 1" : "%83",
				"node 2" : "%68"

			},
			{
				"node 1" : "%83",
				"node 2" : "%74"

			},
			{
				"node 1" : "%83",
				"node 2" : "%69"

			},
			{
				"node 1" : "%83",
				"node 2" : "%80"

			},
			{
				"node 1" : "%83",
				"node 2" : "%91"

			},
			{
				"node 1" : "%83",
				"node 2" : "%71"

			},
			{
				"node 1" : "%83",
				"node 2" : "%72"

			},
			{
				"node 1" : "%83",
				"node 2" : "%73"

			},
			{
				"node 1" : "%83",
				"node 2" : "%75"

			},
			{
				"node 1" : "%83",
				"node 2" : "%76"

			},
			{
				"node 1" : "%83",
				"node 2" : "%77"

			},
			{
				"node 1" : "%83",
				"node 2" : "%78"

			},
			{
				"node 1" : "%83",
				"node 2" : "%79"

			},
			{
				"node 1" : "%83",
				"node 2" : "%84"

			},
			{
				"node 1" : "%83",
				"node 2" : "%85"

			},
			{
				"node 1" : "%83",
				"node 2" : "%86"

			},
			{
				"node 1" : "%83",
				"node 2" : "%87"

			},
			{
				"node 1" : "%83",
				"node 2" : "%88"

			},
			{
				"node 1" : "%83",
				"node 2" : "%89"

			},
			{
				"node 1" : "%83",
				"node 2" : "%90"

			},
			{
				"node 1" : "%60",
				"node 2" : "%61"

			},
			{
				"node 1" : "%61",
				"node 2" : "%62"

			},
			{
				"node 1" : "%62",
				"node 2" : "%63"

			},
			{
				"node 1" : "%62",
				"node 2" : "%64"

			},
			{
				"node 1" : "%62",
				"node 2" : "%65"

			},
			{
				"node 1" : "%62",
				"node 2" : "%66"

			},
			{
				"node 1" : "%62",
				"node 2" : "%67"

			},
			{
				"node 1" : "%63",
				"node 2" : "%64"

			},
			{
				"node 1" : "%64",
				"node 2" : "%65"

			},
			{
				"node 1" : "%65",
				"node 2" : "%66"

			},
			{
				"node 1" : "%66",
				"node 2" : "%67"

			},
			{
				"node 1" : "%67",
				"node 2" : "%68"

			},
			{
				"node 1" : "%67",
				"node 2" : "%74"

			},
			{
				"node 1" : "%68",
				"node 2" : "%74"

			},
			{
				"node 1" : "%68",
				"node 2" : "%69"

			},
			{
				"node 1" : "%68",
				"node 2" : "%80"

			},
			{
				"node 1" : "%68",
				"node 2" : "%91"

			},
			{
				"node 1" : "%68",
				"node 2" : "%71"

			},
			{
				"node 1" : "%68",
				"node 2" : "%72"

			},
			{
				"node 1" : "%68",
				"node 2" : "%73"

			},
			{
				"node 1" : "%68",
				"node 2" : "%75"

			},
			{
				"node 1" : "%68",
				"node 2" : "%76"

			},
			{
				"node 1" : "%68",
				"node 2" : "%77"

			},
			{
				"node 1" : "%68",
				"node 2" : "%78"

			},
			{
				"node 1" : "%68",
				"node 2" : "%79"

			},
			{
				"node 1" : "%74",
				"node 2" : "%69"

			},
			{
				"node 1" : "%74",
				"node 2" : "%80"

			},
			{
				"node 1" : "%74",
				"node 2" : "%91"

			},
			{
				"node 1" : "%74",
				"node 2" : "%71"

			},
			{
				"node 1" : "%74",
				"node 2" : "%72"

			},
			{
				"node 1" : "%74",
				"node 2" : "%73"

			},
			{
				"node 1" : "%74",
				"node 2" : "%75"

			},
			{
				"node 1" : "%74",
				"node 2" : "%76"

			},
			{
				"node 1" : "%74",
				"node 2" : "%77"

			},
			{
				"node 1" : "%74",
				"node 2" : "%78"

			},
			{
				"node 1" : "%74",
				"node 2" : "%79"

			},
			{
				"node 1" : "%69",
				"node 2" : "%80"

			},
			{
				"node 1" : "%69",
				"node 2" : "%91"

			},
			{
				"node 1" : "%69",
				"node 2" : "%71"

			},
			{
				"node 1" : "%69",
				"node 2" : "%72"

			},
			{
				"node 1" : "%69",
				"node 2" : "%73"

			},
			{
				"node 1" : "%69",
				"node 2" : "%75"

			},
			{
				"node 1" : "%69",
				"node 2" : "%76"

			},
			{
				"node 1" : "%69",
				"node 2" : "%77"

			},
			{
				"node 1" : "%69",
				"node 2" : "%78"

			},
			{
				"node 1" : "%69",
				"node 2" : "%79"

			},
			{
				"node 1" : "%80",
				"node 2" : "%91"

			},
			{
				"node 1" : "%80",
				"node 2" : "%71"

			},
			{
				"node 1" : "%80",
				"node 2" : "%72"

			},
			{
				"node 1" : "%80",
				"node 2" : "%73"

			},
			{
				"node 1" : "%80",
				"node 2" : "%75"

			},
			{
				"node 1" : "%80",
				"node 2" : "%76"

			},
			{
				"node 1" : "%80",
				"node 2" : "%77"

			},
			{
				"node 1" : "%80",
				"node 2" : "%78"

			},
			{
				"node 1" : "%80",
				"node 2" : "%79"

			},
			{
				"node 1" : "%91",
				"node 2" : "%71"

			},
			{
				"node 1" : "%91",
				"node 2" : "%72"

			},
			{
				"node 1" : "%91",
				"node 2" : "%73"

			},
			{
				"node 1" : "%91",
				"node 2" : "%75"

			},
			{
				"node 1" : "%91",
				"node 2" : "%76"

			},
			{
				"node 1" : "%91",
				"node 2" : "%77"

			},
			{
				"node 1" : "%91",
				"node 2" : "%78"

			},
			{
				"node 1" : "%91",
				"node 2" : "%79"

			},
			{
				"node 1" : "%91",
				"node 2" : "%84"

			},
			{
				"node 1" : "%91",
				"node 2" : "%85"

			},
			{
				"node 1" : "%91",
				"node 2" : "%86"

			},
			{
				"node 1" : "%91",
				"node 2" : "%87"

			},
			{
				"node 1" : "%91",
				"node 2" : "%88"

			},
			{
				"node 1" : "%91",
				"node 2" : "%89"

			},
			{
				"node 1" : "%91",
				"node 2" : "%90"

			},
			{
				"node 1" : "%91",
				"node 2" : "%92"

			},
			{
				"node 1" : "%91",
				"node 2" : "%93"

			},
			{
				"node 1" : "%71",
				"node 2" : "%72"

			},
			{
				"node 1" : "%71",
				"node 2" : "%73"

			},
			{
				"node 1" : "%72",
				"node 2" : "%73"

			},
			{
				"node 1" : "%72",
				"node 2" : "%75"

			},
			{
				"node 1" : "%72",
				"node 2" : "%76"

			},
			{
				"node 1" : "%72",
				"node 2" : "%77"

			},
			{
				"node 1" : "%72",
				"node 2" : "%78"

			},
			{
				"node 1" : "%72",
				"node 2" : "%79"

			},
			{
				"node 1" : "%72",
				"node 2" : "%84"

			},
			{
				"node 1" : "%72",
				"node 2" : "%85"

			},
			{
				"node 1" : "%72",
				"node 2" : "%86"

			},
			{
				"node 1" : "%72",
				"node 2" : "%87"

			},
			{
				"node 1" : "%72",
				"node 2" : "%88"

			},
			{
				"node 1" : "%72",
				"node 2" : "%89"

			},
			{
				"node 1" : "%72",
				"node 2" : "%90"

			},
			{
				"node 1" : "%72",
				"node 2" : "%92"

			},
			{
				"node 1" : "%72",
				"node 2" : "%93"

			},
			{
				"node 1" : "%72",
				"node 2" : "%.02"

			},
			{
				"node 1" : "%72",
				"node 2" : "%.01"

			},
			{
				"node 1" : "%73",
				"node 2" : "%75"

			},
			{
				"node 1" : "%73",
				"node 2" : "%76"

			},
			{
				"node 1" : "%73",
				"node 2" : "%77"

			},
			{
				"node 1" : "%73",
				"node 2" : "%78"

			},
			{
				"node 1" : "%73",
				"node 2" : "%79"

			},
			{
				"node 1" : "%73",
				"node 2" : "%84"

			},
			{
				"node 1" : "%73",
				"node 2" : "%85"

			},
			{
				"node 1" : "%73",
				"node 2" : "%86"

			},
			{
				"node 1" : "%73",
				"node 2" : "%87"

			},
			{
				"node 1" : "%73",
				"node 2" : "%88"

			},
			{
				"node 1" : "%73",
				"node 2" : "%89"

			},
			{
				"node 1" : "%73",
				"node 2" : "%90"

			},
			{
				"node 1" : "%73",
				"node 2" : "%92"

			},
			{
				"node 1" : "%73",
				"node 2" : "%93"

			},
			{
				"node 1" : "%73",
				"node 2" : "%.02"

			},
			{
				"node 1" : "%75",
				"node 2" : "%76"

			},
			{
				"node 1" : "%76",
				"node 2" : "%77"

			},
			{
				"node 1" : "%77",
				"node 2" : "%78"

			},
			{
				"node 1" : "%77",
				"node 2" : "%79"

			},
			{
				"node 1" : "%78",
				"node 2" : "%79"

			},
			{
				"node 1" : "%84",
				"node 2" : "%85"

			},
			{
				"node 1" : "%85",
				"node 2" : "%86"

			},
			{
				"node 1" : "%86",
				"node 2" : "%87"

			},
			{
				"node 1" : "%86",
				"node 2" : "%88"

			},
			{
				"node 1" : "%87",
				"node 2" : "%88"

			},
			{
				"node 1" : "%89",
				"node 2" : "%90"

			},
			{
				"node 1" : "%90",
				"node 2" : "%92"

			},
			{
				"node 1" : "%.02",
				"node 2" : "%.01"

			},
			{
				"node 1" : "%.02",
				"node 2" : "%95"

			},
			{
				"node 1" : "%.02",
				"node 2" : "%96"

			},
			{
				"node 1" : "%.01",
				"node 2" : "%95"

			},
			{
				"node 1" : "%95",
				"node 2" : "%96"

			}
		]
	},
	"dereferenceable" : 	{
		"nodes" : {
			"%0" : {
				"type" : "label",
				"uses" : [1, 2, 6],
				"uses deepness" : [0, 0, 0]
			},
			"%2" : {
				"type" : "ptr",
				"uses" : [2, 3, 5],
				"uses deepness" : [0, 0, 0]
			},
			"%3" : {
				"type" : "",
				"uses" : [3, 4],
				"uses deepness" : [0, 0]
			},
			"%4" : {
				"type" : "ptr",
				"uses" : [4, 5],
				"uses deepness" : [0, 0]
			}
		},
		"edges" : [
			{
				"node 1" : "%0",
				"node 2" : "%2"

			},
			{
				"node 1" : "%0",
				"node 2" : "%3"

			},
			{
				"node 1" : "%0",
				"node 2" : "%4"

			},
			{
				"node 1" : "%2",
				"node 2" : "%3"

			},
			{
				"node 1" : "%2",
				"node 2" : "%4"

			},
			{
				"node 1" : "%3",
				"node 2" : "%4"

			}
		]
	},
	"i64*" : 	{
		"nodes" : {
			"%0" : {
				"type" : "label",
				"uses" : [1, 3, 13],
				"uses deepness" : [0, 0, 0]
			},
			"%1" : {
				"type" : "",
				"uses" : [1, 2],
				"uses deepness" : [0, 0]
			},
			"%2" : {
				"type" : "",
				"uses" : [1, 11, 20],
				"uses deepness" : [0, 0, 0]
			},
			"%4" : {
				"type" : "ptr",
				"uses" : [2, 4],
				"uses deepness" : [0, 0]
			},
			"%5" : {
				"type" : "ptr",
				"uses" : [3, 4],
				"uses deepness" : [0, 0]
			},
			"%6" : {
				"type" : "i64",
				"uses" : [4, 5],
				"uses deepness" : [0, 0]
			},
			"%7" : {
				"type" : "i64",
				"uses" : [5, 6, 10, 14, 19],
				"uses deepness" : [0, 0, 0, 0, 0]
			},
			"%8" : {
				"type" : "label",
				"uses" : [6, 7],
				"uses deepness" : [0, 0]
			},
			"%9" : {
				"type" : "label",
				"uses" : [7, 18],
				"uses deepness" : [0, 0]
			},
			"%15" : {
				"type" : "label",
				"uses" : [7, 16],
				"uses deepness" : [0, 0]
			},
			"%3" : {
				"type" : "",
				"uses" : [9, 18],
				"uses deepness" : [0, 0]
			},
			"%10" : {
				"type" : "i64",
				"uses" : [10, 11],
				"uses deepness" : [0, 0]
			},
			"%11" : {
				"type" : "ptr",
				"uses" : [11, 12],
				"uses deepness" : [0, 0]
			},
			"%12" : {
				"type" : "ptr",
				"uses" : [12, 15],
				"uses deepness" : [0, 0]
			},
			"%13" : {
				"type" : "ptr",
				"uses" : [13, 15],
				"uses deepness" : [0, 0]
			},
			"%14" : {
				"type" : "i64",
				"uses" : [14, 15],
				"uses deepness" : [0, 0]
			},
			"%16" : {
				"type" : "i64",
				"uses" : [19, 20],
				"uses deepness" : [0, 0]
			},
			"%17" : {
				"type" : "ptr",
				"uses" : [20, 21],
				"uses deepness" : [0, 0]
			}
		},
		"edges" : [
			{
				"node 1" : "%0",
				"node 2" : "%1"

			},
			{
				"node 1" : "%0",
				"node 2" : "%2"

			},
			{
				"node 1" : "%0",
				"node 2" : "%4"

			},
			{
				"node 1" : "%0",
				"node 2" : "%5"

			},
			{
				"node 1" : "%0",
				"node 2" : "%6"

			},
			{
				"node 1" : "%0",
				"node 2" : "%7"

			},
			{
				"node 1" : "%0",
				"node 2" : "%8"

			},
			{
				"node 1" : "%0",
				"node 2" : "%9"

			},
			{
				"node 1" : "%0",
				"node 2" : "%15"

			},
			{
				"node 1" : "%0",
				"node 2" : "%3"

			},
			{
				"node 1" : "%0",
				"node 2" : "%10"

			},
			{
				"node 1" : "%0",
				"node 2" : "%11"

			},
			{
				"node 1" : "%0",
				"node 2" : "%12"

			},
			{
				"node 1" : "%0",
				"node 2" : "%13"

			},
			{
				"node 1" : "%1",
				"node 2" : "%2"

			},
			{
				"node 1" : "%1",
				"node 2" : "%4"

			},
			{
				"node 1" : "%2",
				"node 2" : "%4"

			},
			{
				"node 1" : "%2",
				"node 2" : "%5"

			},
			{
				"node 1" : "%2",
				"node 2" : "%6"

			},
			{
				"node 1" : "%2",
				"node 2" : "%7"

			},
			{
				"node 1" : "%2",
				"node 2" : "%8"

			},
			{
				"node 1" : "%2",
				"node 2" : "%9"

			},
			{
				"node 1" : "%2",
				"node 2" : "%15"

			},
			{
				"node 1" : "%2",
				"node 2" : "%3"

			},
			{
				"node 1" : "%2",
				"node 2" : "%10"

			},
			{
				"node 1" : "%2",
				"node 2" : "%11"

			},
			{
				"node 1" : "%2",
				"node 2" : "%12"

			},
			{
				"node 1" : "%2",
				"node 2" : "%13"

			},
			{
				"node 1" : "%2",
				"node 2" : "%14"

			},
			{
				"node 1" : "%2",
				"node 2" : "%16"

			},
			{
				"node 1" : "%2",
				"node 2" : "%17"

			},
			{
				"node 1" : "%4",
				"node 2" : "%5"

			},
			{
				"node 1" : "%4",
				"node 2" : "%6"

			},
			{
				"node 1" : "%5",
				"node 2" : "%6"

			},
			{
				"node 1" : "%6",
				"node 2" : "%7"

			},
			{
				"node 1" : "%7",
				"node 2" : "%8"

			},
			{
				"node 1" : "%7",
				"node 2" : "%9"

			},
			{
				"node 1" : "%7",
				"node 2" : "%15"

			},
			{
				"node 1" : "%7",
				"node 2" : "%3"

			},
			{
				"node 1" : "%7",
				"node 2" : "%10"

			},
			{
				"node 1" : "%7",
				"node 2" : "%11"

			},
			{
				"node 1" : "%7",
				"node 2" : "%12"

			},
			{
				"node 1" : "%7",
				"node 2" : "%13"

			},
			{
				"node 1" : "%7",
				"node 2" : "%14"

			},
			{
				"node 1" : "%7",
				"node 2" : "%16"

			},
			{
				"node 1" : "%8",
				"node 2" : "%9"

			},
			{
				"node 1" : "%8",
				"node 2" : "%15"

			},
			{
				"node 1" : "%9",
				"node 2" : "%15"

			},
			{
				"node 1" : "%9",
				"node 2" : "%3"

			},
			{
				"node 1" : "%9",
				"node 2" : "%10"

			},
			{
				"node 1" : "%9",
				"node 2" : "%11"

			},
			{
				"node 1" : "%9",
				"node 2" : "%12"

			},
			{
				"node 1" : "%9",
				"node 2" : "%13"

			},
			{
				"node 1" : "%9",
				"node 2" : "%14"

			},
			{
				"node 1" : "%15",
				"node 2" : "%3"

			},
			{
				"node 1" : "%15",
				"node 2" : "%10"

			},
			{
				"node 1" : "%15",
				"node 2" : "%11"

			},
			{
				"node 1" : "%15",
				"node 2" : "%12"

			},
			{
				"node 1" : "%15",
				"node 2" : "%13"

			},
			{
				"node 1" : "%15",
				"node 2" : "%14"

			},
			{
				"node 1" : "%3",
				"node 2" : "%10"

			},
			{
				"node 1" : "%3",
				"node 2" : "%11"

			},
			{
				"node 1" : "%3",
				"node 2" : "%12"

			},
			{
				"node 1" : "%3",
				"node 2" : "%13"

			},
			{
				"node 1" : "%3",
				"node 2" : "%14"

			},
			{
				"node 1" : "%10",
				"node 2" : "%11"

			},
			{
				"node 1" : "%11",
				"node 2" : "%12"

			},
			{
				"node 1" : "%12",
				"node 2" : "%13"

			},
			{
				"node 1" : "%12",
				"node 2" : "%14"

			},
			{
				"node 1" : "%13",
				"node 2" : "%14"

			},
			{
				"node 1" : "%16",
				"node 2" : "%17"

			}
		]
	},
	"i64" : 	{
		"nodes" : {
			"%0" : {
				"type" : "label",
				"uses" : [1, 2],
				"uses deepness" : [0, 0]
			},
			"%1" : {
				"type" : "",
				"uses" : [1, 4],
				"uses deepness" : [0, 0]
			},
			"%3" : {
				"type" : "",
				"uses" : [2, 3],
				"uses deepness" : [0, 0]
			},
			"%4" : {
				"type" : "",
				"uses" : [3, 6],
				"uses deepness" : [0, 0]
			},
			"%5" : {
				"type" : "",
				"uses" : [4, 5],
				"uses deepness" : [0, 0]
			},
			"%6" : {
				"type" : "",
				"uses" : [5, 7],
				"uses deepness" : [0, 0]
			},
			"%7" : {
				"type" : "ptr",
				"uses" : [6, 8],
				"uses deepness" : [0, 0]
			},
			"%8" : {
				"type" : "ptr",
				"uses" : [7, 8],
				"uses deepness" : [0, 0]
			},
			"%9" : {
				"type" : "i64",
				"uses" : [8, 9],
				"uses deepness" : [0, 0]
			},
			"%10" : {
				"type" : "i64",
				"uses" : [9, 10],
				"uses deepness" : [0, 0]
			}
		},
		"edges" : [
			{
				"node 1" : "%0",
				"node 2" : "%1"

			},
			{
				"node 1" : "%0",
				"node 2" : "%3"

			},
			{
				"node 1" : "%1",
				"node 2" : "%3"

			},
			{
				"node 1" : "%1",
				"node 2" : "%4"

			},
			{
				"node 1" : "%1",
				"node 2" : "%5"

			},
			{
				"node 1" : "%3",
				"node 2" : "%4"

			},
			{
				"node 1" : "%4",
				"node 2" : "%5"

			},
			{
				"node 1" : "%4",
				"node 2" : "%6"

			},
			{
				"node 1" : "%4",
				"node 2" : "%7"

			},
			{
				"node 1" : "%5",
				"node 2" : "%6"

			},
			{
				"node 1" : "%6",
				"node 2" : "%7"

			},
			{
				"node 1" : "%6",
				"node 2" : "%8"

			},
			{
				"node 1" : "%7",
				"node 2" : "%8"

			},
			{
				"node 1" : "%7",
				"node 2" : "%9"

			},
			{
				"node 1" : "%8",
				"node 2" : "%9"

			},
			{
				"node 1" : "%9",
				"node 2" : "%10"

			}
		]
	},
	"hidden" : 	{
		"nodes" : {
			"%0" : {
				"type" : "label",
				"uses" : [1, 2],
				"uses deepness" : [0, 0]
			},
			"%2" : {
				"type" : "ptr",
				"uses" : [2],
				"uses deepness" : [0]
			}
		},
		"edges" : [
			{
				"node 1" : "%0",
				"node 2" : "%2"

			}
		]
	},
	"zeroext" : 	{
		"nodes" : {
			"%0" : {
				"type" : "label",
				"uses" : [1],
				"uses deepness" : [0]
			},
			"%1" : {
				"type" : "",
				"uses" : [1, 5],
				"uses deepness" : [0, 0]
			},
			"%2" : {
				"type" : "",
				"uses" : [1, 4],
				"uses deepness" : [0, 0]
			},
			"%4" : {
				"type" : "ptr",
				"uses" : [2, 3, 6],
				"uses deepness" : [0, 0, 0]
			},
			"%5" : {
				"type" : "ptr",
				"uses" : [3, 4],
				"uses deepness" : [0, 0]
			},
			"%6" : {
				"type" : "ptr",
				"uses" : [5, 8],
				"uses deepness" : [0, 0]
			},
			"%7" : {
				"type" : "ptr",
				"uses" : [6, 7],
				"uses deepness" : [0, 0]
			},
			"%8" : {
				"type" : "ptr",
				"uses" : [7, 8],
				"uses deepness" : [0, 0]
			},
			"%9" : {
				"type" : "i8",
				"uses" : [8, 9],
				"uses deepness" : [0, 0]
			}
		},
		"edges" : [
			{
				"node 1" : "%0",
				"node 2" : "%1"

			},
			{
				"node 1" : "%0",
				"node 2" : "%2"

			},
			{
				"node 1" : "%1",
				"node 2" : "%2"

			},
			{
				"node 1" : "%1",
				"node 2" : "%4"

			},
			{
				"node 1" : "%1",
				"node 2" : "%5"

			},
			{
				"node 1" : "%1",
				"node 2" : "%6"

			},
			{
				"node 1" : "%2",
				"node 2" : "%4"

			},
			{
				"node 1" : "%2",
				"node 2" : "%5"

			},
			{
				"node 1" : "%4",
				"node 2" : "%5"

			},
			{
				"node 1" : "%4",
				"node 2" : "%6"

			},
			{
				"node 1" : "%4",
				"node 2" : "%7"

			},
			{
				"node 1" : "%6",
				"node 2" : "%7"

			},
			{
				"node 1" : "%6",
				"node 2" : "%8"

			},
			{
				"node 1" : "%6",
				"node 2" : "%9"

			},
			{
				"node 1" : "%7",
				"node 2" : "%8"

			},
			{
				"node 1" : "%8",
				"node 2" : "%9"

			}
		]
	}
}